Workbook
Name SKU_List: 'Item Master'!$A$4:$A$53
Name TXN_List: 'Log Transaction'!$B$4:$B$303

Sheet Start Here
A1: =HYPERLINK("#'Dashboard'!A1","🏠 Dashboard") | C1: =HYPERLINK("#'Item Master'!A1","📦 Products") | D1: =HYPERLINK("#'Log Transaction'!A1","✍️ Log Sale") | E1: =HYPERLINK("#'Invoice Generator'!A1","🧾 Invoice") | F1: =HYPERLINK("#'Start Here'!A1","🚀 Start Here")
B4: MOMENTUM MIND STORE
B5: 📦 Inventory Manager PRO
B6: Track stock, log every sale, and send invoices — from your phone.
B8: 📦 STEP 1 — Add your products
B9: Open the Products screen and fill one row per item. SKU must be unique — it is the key that powers everything else.
B11: ⚙️ STEP 2 — Set your business details
B12: Open Settings and enter your shop name, contact details, tax rate and invoice prefix. Every invoice reads from there.
B14: ✍️ STEP 3 — Log every movement
B15: On the Log Sale screen, tap a new row. Pick the SKU from the dropdown, choose IN (stock received), OUT (sold) or SHRINKAGE (damaged/lost), and enter the quantity. The Total fills itself.
B17: 🧾 STEP 4 — Generate an invoice
B18: Type or pick a Transaction ID at the top of the Invoice screen. Every line for that ID appears instantly. Share ▸ Export as PDF.
B20: 🏠 STEP 5 — Watch the Dashboard
... B23: 🎨 COLOUR KEY
B24: 🟡 Yellow cells | C24: You type here.
B25: ⬜ White cells | C25: Calculated automatically — do not overwrite.
B26: 🟦 Dark bar (top) | C26: Tap any label to jump between screens.
B28: 💬 NEED HELP?
B29: ✉️ Support email | C29: =HYPERLINK("mailto:support@momentummindstore.com?subject=Inventory%20Manager%20PRO%20-%20Support","support@momentummindstore.com")
B30: 🛍️ Etsy shop | C30: =HYPERLINK("https://www.etsy.com/shop/MomentumMindStore","etsy.com/shop/MomentumMindStore")
B31: 📖 Video walkthrough | C31: =HYPERLINK("https://www.momentummindstore.com/inventory-pro-guide","Watch the 4-minute setup video")
B32: ⭐ Loved it? | C32: =HYPERLINK("https://www.etsy.com/your/purchases","Leave a review — it genuinely helps a small shop")
B34: © Momentum Mind Store — single-shop licence. No resale or redistribution of this file.

Sheet Dashboard
A1: =HYPERLINK("#'Dashboard'!A1","🏠 Dashboard") | C1: =HYPERLINK("#'Item Master'!A1","📦 Products") | E1: =HYPERLINK("#'Log Transaction'!A1","✍️ Log Sale") | F1: =HYPERLINK("#'Invoice Generator'!A1","🧾 Invoice") | G1: =HYPERLINK("#'Start Here'!A1","🚀 Start Here")
A4: LIVE OVERVIEW
A5: 🏠 Dashboard
A6: Stock recalculates the moment you log a transaction.
A7: =COUNTA('Item Master'!$A$4:$A$53) | C7: =SUM($E$9:$E$58) | E7: =SUM($I$9:$I$58) | G7: =COUNTIF($F$9:$F$58,"⚠️ REORDER NOW")
A8: SKU | B8: 📦 Product | C8: ⬇ Total IN | D8: ⬆ Total OUT | E8: 📊 Current Stock | F8: 🚦 Stock Status | G8: 💬 WhatsApp Order | H8: ✉️ Email Order | I8: Value
A9: =IF(INDEX('Item Master'!$A$4:$A$53,1)="","",INDEX('Item Master'!$A$4:$A$53,1)) | B9: =IF($A9="","",_xlfn.XLOOKUP($A9,'Item Master'!$A$4:$A$53,'Item Master'!$B$4:$B$53,"")) | C9: =IF($A9="","",SUMIFS('Log Transaction'!$E$4:$E$303,'Log Transaction'!$C$4:$C$303,$A9,'Log Transaction'!$D$4:$D$303,"IN")) | D9: =IF($A9="","",SUMIFS('Log Transaction'!$E$4:$E$303,'Log Transaction'!$C$4:$C$303,$A9,'Log Transaction'!$D$4:$D$303,"OUT")+SUMIFS('Log Transaction'!$E$4:$E$303,'Log Transaction'!$C$4:$C$303,$A9,'Log Transaction'!$D$4:$D$303,"SHRINKAGE")) | E9: =IF($A9="","",$C9-$D9) | F9: =IF($A9="","",IF($E9<=_xlfn.XLOOKUP($A9,'Item Master'!$A$4:$A$53,'Item Master'!$F$4:$F$53,0)*0.1,"⚠️ REORDER NOW","✅ IN STOCK")) | G9: =IF($A9="","",IF($F9="⚠️ REORDER NOW",HYPERLINK("https://wa.me/"&SUBSTITUTE(SUBSTITUTE(SUBSTITUTE(SUBSTITUTE(SUBSTITUTE(SUBSTITUTE(_xlfn.XLOOKUP($A9,'Item Master'!$A$4:$A$53,'Item Master'!$I$4:$I$53,""),"+",""),"-","")," ",""),"(",""),")",""),".","")&"?text="&SUBSTITUTE("Hello "&_xlfn.XLOOKUP($A9,'Item Master'!$A$4:$A$53,'Item Master'!$H$4:$H$53,"Supplier")&", we urgently need more "&$B9&". Current stock is only "&TEXT($E9,"0")&" units. Please confirm availability and your fastest lead time. Thank you - Momentum Mind Store."," ","%20"),"💬 ORDER NOW"),"")) | H9: =IF($A9="","",IF($F9="⚠️ REORDER NOW",HYPERLINK("mailto:"&_xlfn.XLOOKUP($A9,'Item Master'!$A$4:$A$53,'Item Master'!$J$4:$J$53,"")&"?subject="&SUBSTITUTE("URGENT restock request - "&$B9&" ("&$A9&")"," ","%20")&"&body="&SUBSTITUTE(SUBSTITUTE("Hello "&_xlfn.XLOOKUP($A9,'Item Master'!$A$4:$A$53,'Item Master'!$H$4:$H$53,"Supplier")&"," & CHAR(10) & "We urgently need to restock "&$B9&" (SKU "&$A9&"). Our current stock is "&TEXT($E9,"0")&" units, which is below our reorder threshold." & CHAR(10) & "Please confirm availability, unit price and lead time by return." & CHAR(10) & "Kind regards," & CHAR(10) & "Momentum Mind Store"," ","%20"),CHAR(10),"%0D%0A"),"✉️ EMAIL"),"")) | I9: =IF($A9="","",$E9*_xlfn.XLOOKUP($A9,'Item Master'!$A$4:$A$53,'Item Master'!$D$4:$D$53,0))
A10: =IF(INDEX('Item Master'!$A$4:$A$53,2)="","",INDEX('Item Master'!$A$4:$A$53,2)) | B10: =IF($A10="","",_xlfn.XLOOKUP($A10,'Item Master'!$A$4:$A$53,'Item Master'!$B$4:$B$53,"")) | C10: =IF($A10="","",SUMIFS('Log Transaction'!$E$4:$E$303,'Log Transaction'!$C$4:$C$303,$A10,'Log Transaction'!$D$4:$D$303,"IN")) | D10: =IF($A10="","",SUMIFS('Log Transaction'!$E$4:$E$303,'Log Transaction'!$C$4:$C$303,$A10,'Log Transaction'!$D$4:$D$303,"OUT")+SUMIFS('Log Transaction'!$E$4:$E$303,'Log Transaction'!$C$4:$C$303,$A10,'Log Transaction'!$D$4:$D$303,"SHRINKAGE")) | E10: =IF($A10="","",$C10-$D10) | F10: =IF($A10="","",IF($E10<=_xlfn.XLOOKUP($A10,'Item Master'!$A$4:$A$53,'Item Master'!$F$4:$F$53,0)*0.1,"⚠️ REORDER NOW","✅ IN STOCK")) | G10: =IF($A10="","",IF($F10="⚠️ REORDER NOW",HYPERLINK("https://wa.me/"&SUBSTITUTE(SUBSTITUTE(SUBSTITUTE(SUBSTITUTE(SUBSTITUTE(SUBSTITUTE(_xlfn.XLOOKUP($A10,'Item Master'!$A$4:$A$53,'Item Master'!$I$4:$I$53,""),"+",""),"-","")," ",""),"(",""),")",""),".","")&"?text="&SUBSTITUTE("Hello "&_xlfn.XLOOKUP($A10,'Item Master'!$A$4:$A$53,'Item Master'!$H$4:$H$53,"Supplier")&", we urgently need more "&$B10&". Current stock is only "&TEXT($E10,"0")&" units. Please confirm availability and your fastest lead time. Thank you - Momentum Mind Store."," ","%20"),"💬 ORDER NOW"),"")) | H10: =IF($A10="","",IF($F10="⚠️ REORDER NOW",HYPERLINK("mailto:"&_xlfn.XLOOKUP($A10,'Item Master'!$A$4:$A$53,'Item Master'!$J$4:$J$53,"")&"?subject="&SUBSTITUTE("URGENT restock request - "&$B10&" ("&$A10&")"," ","%20")&"&body="&SUBSTITUTE(SUBSTITUTE("Hello "&_xlfn.XLOOKUP($A10,'Item Master'!$A$4:$A$53,'Item Master'!$H$4:$H$53,"Supplier")&"," & CHAR(10) & "We urgently need to restock "&$B10&" (SKU "&$A10&"). Our current stock is "&TEXT($E10,"0")&" units, which is below our reorder threshold." & CHAR(10) & "Please confirm availability, unit price and lead time by return." & CHAR(10) & "Kind regards," & CHAR(10) & "Momentum Mind Store"," ","%20"),CHAR(10),"%0D%0A"),"✉️ EMAIL"),"")) | I10: =IF($A10="","",$E10*_xlfn.XLOOKUP($A10,'Item Master'!$A$4:$A$53,'Item Master'!$D$4:$D$53,0))
A11: =IF(INDEX('Item Master'!$A$4:$A$53,3)="","",INDEX('Item Master'!$A$4:$A$53,3)) | B11: =IF($A11="","",_xlfn.XLOOKUP($A11,'Item Master'!$A$4:$A$53,'Item Master'!$B$4:$B$53,"")) | C11: =IF($A11="","",SUMIFS('Log Transaction'!$E$4:$E$303,'Log Transaction'!$C$4:$C$303,$A11,'Log Transaction'!$D$4:$D$303,"IN")) | D11: =IF($A11="","",SUMIFS('Log Transaction'!$E$4:$E$303,'Log Transaction'!$C$4:$C$303,$A11,'Log Transaction'!$D$4:$D$303,"OUT")+SUMIFS('Log Transaction'!$E$4:$E$303,'Log Transaction'!$C$4:$C$303,$A11,'Log Transaction'!$D$4:$D$303,"SHRINKAGE")) | E11: =IF($A11="","",$C11-$D11) | F11: =IF($A11="","",IF($E11<=_xlfn.XLOOKUP($A11,'Item Master'!$A$4:$A$53,'Item Master'!$F$4:$F$53,0)*0.1,"⚠️ REORDER NOW","✅ IN STOCK")) | G11: =IF($A11="","",IF($F11="⚠️ REORDER NOW",HYPERLINK("https://wa.me/"&SUBSTITUTE(SUBSTITUTE(SUBSTITUTE(SUBSTITUTE(SUBSTITUTE(SUBSTITUTE(_xlfn.XLOOKUP($A11,'Item Master'!$A$4:$A$53,'Item Master'!$I$4:$I$53,""),"+",""),"-","")," ",""),"(",""),")",""),".","")&"?text="&SUBSTITUTE("Hello "&_xlfn.XLOOKUP($A11,'Item Master'!$A$4:$A$53,'Item Master'!$H$4:$H$53,"Supplier")&", we urgently need more "&$B11&". Current stock is only "&TEXT($E11,"0")&" units. Please confirm availability and your fastest lead time. Thank you - Momentum Mind Store."," ","%20"),"💬 ORDER NOW"),"")) | H11: =IF($A11="","",IF($F11="⚠️ REORDER NOW",HYPERLINK("mailto:"&_xlfn.XLOOKUP($A11,'Item Master'!$A$4:$A$53,'Item Master'!$J$4:$J$53,"")&"?subject="&SUBSTITUTE("URGENT restock request - "&$B11&" ("&$A11&")"," ","%20")&"&body="&SUBSTITUTE(SUBSTITUTE("Hello "&_xlfn.XLOOKUP($A11,'Item Master'!$A$4:$A$53,'Item Master'!$H$4:$H$53,"Supplier")&"," & CHAR(10) & "We urgently need to restock "&$B11&" (SKU "&$A11&"). Our current stock is "&TEXT($E11,"0")&" units, which is below our reorder threshold." & CHAR(10) & "Please confirm availability, unit price and lead time by return." & CHAR(10) & "Kind regards," & CHAR(10) & "Momentum Mind Store"," ","%20"),CHAR(10),"%0D%0A"),"✉️ EMAIL"),"")) | I11: =IF($A11="","",$E11*_xlfn.XLOOKUP($A11,'Item Master'!$A$4:$A$53,'Item Master'!$D$4:$D$53,0))
A12: =IF(INDEX('Item Master'!$A$4:$A$53,4)="","",INDEX('Item Master'!$A$4:$A$53,4)) | B12: =IF($A12="","",_xlfn.XLOOKUP($A12,'Item Master'!$A$4:$A$53,'Item Master'!$B$4:$B$53,"")) | C12: =IF($A12="","",SUMIFS('Log Transaction'!$E$4:$E$303,'Log Transaction'!$C$4:$C$303,$A12,'Log Transaction'!$D$4:$D$303,"IN")) | D12: =IF($A12="","",SUMIFS('Log Transaction'!$E$4:$E$303,'Log Transaction'!$C$4:$C$303,$A12,'Log Transaction'!$D$4:$D$303,"OUT")+SUMIFS('Log Transaction'!$E$4:$E$303,'Log Transaction'!$C$4:$C$303,$A12,'Log Transaction'!$D$4:$D$303,"SHRINKAGE")) | E12: =IF($A12="","",$C12-$D12) | F12: =IF($A12="","",IF($E12<=_xlfn.XLOOKUP($A12,'Item Master'!$A$4:$A$53,'Item Master'!$F$4:$F$53,0)*0.1,"⚠️ REORDER NOW","✅ IN STOCK")) | G12: =IF($A12="","",IF($F12="⚠️ REORDER NOW",HYPERLINK("https://wa.me/"&SUBSTITUTE(SUBSTITUTE(SUBSTITUTE(SUBSTITUTE(SUBSTITUTE(SUBSTITUTE(_xlfn.XLOOKUP($A12,'Item Master'!$A$4:$A$53,'Item Master'!$I$4:$I$53,""),"+",""),"-","")," ",""),"(",""),")",""),".","")&"?text="&SUBSTITUTE("Hello "&_xlfn.XLOOKUP($A12,'Item Master'!$A$4:$A$53,'Item Master'!$H$4:$H$53,"Supplier")&", we urgently need more "&$B12&". Current stock is only "&TEXT($E12,"0")&" units. Please confirm availability and your fastest lead time. Thank you - Momentum Mind Store."," ","%20"),"💬 ORDER NOW"),"")) | H12: =IF($A12="","",IF($F12="⚠️ REORDER NOW",HYPERLINK("mailto:"&_xlfn.XLOOKUP($A12,'Item Master'!$A$4:$A$53,'Item Master'!$J$4:$J$53,"")&"?subject="&SUBSTITUTE("URGENT restock request - "&$B12&" ("&$A12&")"," ","%20")&"&body="&SUBSTITUTE(SUBSTITUTE("Hello "&_xlfn.XLOOKUP($A12,'Item Master'!$A$4:$A$53,'Item Master'!$H$4:$H$53,"Supplier")&"," & CHAR(10) & "We urgently need to restock "&$B12&" (SKU "&$A12&"). Our current stock is "&TEXT($E12,"0")&" units, which is below our reorder threshold." & CHAR(10) & "Please confirm availability, unit price and lead time by return." & CHAR(10) & "Kind regards," & CHAR(10) & "Momentum Mind Store"," ","%20"),CHAR(10),"%0D%0A"),"✉️ EMAIL"),"")) | I12: =IF($A12="","",$E12*_xlfn.XLOOKUP($A12,'Item Master'!$A$4:$A$53,'Item Master'!$D$4:$D$53,0))
A13: =IF(INDEX('Item Master'!$A$4:$A$53,5)="","",INDEX('Item Master'!$A$4:$A$53,5)) | B13: =IF($A13="","",_xlfn.XLOOKUP($A13,'Item Master'!$A$4:$A$53,'Item Master'!$B$4:$B$53,"")) | C13: =IF($A13="","",SUMIFS('Log Transaction'!$E$4:$E$303,'Log Transaction'!$C$4:$C$303,$A13,'Log Transaction'!$D$4:$D$303,"IN")) | D13: =IF($A13="","",SUMIFS('Log Transaction'!$E$4:$E$303,'Log Transaction'!$C$4:$C$303,$A13,'Log Transaction'!$D$4:$D$303,"OUT")+SUMIFS('Log Transaction'!$E$4:$E$303,'Log Transaction'!$C$4:$C$303,$A13,'Log Transaction'!$D$4:$D$303,"SHRINKAGE")) | E13: =IF($A13="","",$C13-$D13) | F13: =IF($A13="","",IF($E13<=_xlfn.XLOOKUP($A13,'Item Master'!$A$4:$A$53,'Item Master'!$F$4:$F$53,0)*0.1,"⚠️ REORDER NOW","✅ IN STOCK")) | G13: =IF($A13="","",IF($F13="⚠️ REORDER NOW",HYPERLINK("https://wa.me/"&SUBSTITUTE(SUBSTITUTE(SUBSTITUTE(SUBSTITUTE(SUBSTITUTE(SUBSTITUTE(_xlfn.XLOOKUP($A13,'Item Master'!$A$4:$A$53,'Item Master'!$I$4:$I$53,""),"+",""),"-","")," ",""),"(",""),")",""),".","")&"?text="&SUBSTITUTE("Hello "&_xlfn.XLOOKUP($A13,'Item Master'!$A$4:$A$53,'Item Master'!$H$4:$H$53,"Supplier")&", we urgently need more "&$B13&". Current stock is only "&TEXT($E13,"0")&" units. Please confirm availability and your fastest lead time. Thank you - Momentum Mind Store."," ","%20"),"💬 ORDER NOW"),"")) | H13: =IF($A13="","",IF($F13="⚠️ REORDER NOW",HYPERLINK("mailto:"&_xlfn.XLOOKUP($A13,'Item Master'!$A$4:$A$53,'Item Master'!$J$4:$J$53,"")&"?subject="&SUBSTITUTE("URGENT restock request - "&$B13&" ("&$A13&")"," ","%20")&"&body="&SUBSTITUTE(SUBSTITUTE("Hello "&_xlfn.XLOOKUP($A13,'Item Master'!$A$4:$A$53,'Item Master'!$H$4:$H$53,"Supplier")&"," & CHAR(10) & "We urgently need to restock "&$B13&" (SKU "&$A13&"). Our current stock is "&TEXT($E13,"0")&" units, which is below our reorder threshold." & CHAR(10) & "Please confirm availability, unit price and lead time by return." & CHAR(10) & "Kind regards," & CHAR(10) & "Momentum Mind Store"," ","%20"),CHAR(10),"%0D%0A"),"✉️ EMAIL"),"")) | I13: =IF($A13="","",$E13*_xlfn.XLOOKUP($A13,'Item Master'!$A$4:$A$53,'Item Master'!$D$4:$D$53,0))
A14: =IF(INDEX('Item Master'!$A$4:$A$53,6)="","",INDEX('Item Master'!$A$4:$A$53,6)) | B14: =IF($A14="","",_xlfn.XLOOKUP($A14,'Item Master'!$A$4:$A$53,'Item Master'!$B$4:$B$53,"")) | C14: =IF($A14="","",SUMIFS('Log Transaction'!$E$4:$E$303,'Log Transaction'!$C$4:$C$303,$A14,'Log Transaction'!$D$4:$D$303,"IN")) | D14: =IF($A14="","",SUMIFS('Log Transaction'!$E$4:$E$303,'Log Transaction'!$C$4:$C$303,$A14,'Log Transaction'!$D$4:$D$303,"OUT")+SUMIFS('Log Transaction'!$E$4:$E$303,'Log Transaction'!$C$4:$C$303,$A14,'Log Transaction'!$D$4:$D$303,"SHRINKAGE")) | E14: =IF($A14="","",$C14-$D14) | F14: =IF($A14="","",IF($E14<=_xlfn.XLOOKUP($A14,'Item Master'!$A$4:$A$53,'Item Master'!$F$4:$F$53,0)*0.1,"⚠️ REORDER NOW","✅ IN STOCK")) | G14: =IF($A14="","",IF($F14="⚠️ REORDER NOW",HYPERLINK("https://wa.me/"&SUBSTITUTE(SUBSTITUTE(SUBSTITUTE(SUBSTITUTE(SUBSTITUTE(SUBSTITUTE(_xlfn.XLOOKUP($A14,'Item Master'!$A$4:$A$53,'Item Master'!$I$4:$I$53,""),"+",""),"-","")," ",""),"(",""),")",""),".","")&"?text="&SUBSTITUTE("Hello "&_xlfn.XLOOKUP($A14,'Item Master'!$A$4:$A$53,'Item Master'!$H$4:$H$53,"Supplier")&", we urgently need more "&$B14&". Current stock is only "&TEXT($E14,"0")&" units. Please confirm availability and your fastest lead time. Thank you - Momentum Mind Store."," ","%20"),"💬 ORDER NOW"),"")) | H14: =IF($A14="","",IF($F14="⚠️ REORDER NOW",HYPERLINK("mailto:"&_xlfn.XLOOKUP($A14,'Item Master'!$A$4:$A$53,'Item Master'!$J$4:$J$53,"")&"?subject="&SUBSTITUTE("URGENT restock request - "&$B14&" ("&$A14&")"," ","%20")&"&body="&SUBSTITUTE(SUBSTITUTE("Hello "&_xlfn.XLOOKUP($A14,'Item Master'!$A$4:$A$53,'Item Master'!$H$4:$H$53,"Supplier")&"," & CHAR(10) & "We urgently need to restock "&$B14&" (SKU "&$A14&"). Our current stock is "&TEXT($E14,"0")&" units, which is below our reorder threshold." & CHAR(10) & "Please confirm availability, unit price and lead time by return." & CHAR(10) & "Kind regards," & CHAR(10) & "Momentum Mind Store"," ","%20"),CHAR(10),"%0D%0A"),"✉️ EMAIL"),"")) | I14: =IF($A14="","",$E14*_xlfn.XLOOKUP($A14,'Item Master'!$A$4:$A$53,'Item Master'!$D$4:$D$53,0))
A15: =IF(INDEX('Item Master'!$A$4:$A$53,7)="","",INDEX('Item Master'!$A$4:$A$53,7)) | B15: =IF($A15="","",_xlfn.XLOOKUP($A15,'Item Master'!$A$4:$A$53,'Item Master'!$B$4:$B$53,"")) | C15: =IF($A15="","",SUMIFS('Log Transaction'!$E$4:$E$303,'Log Transaction'!$C$4:$C$303,$A15,'Log Transaction'!$D$4:$D$303,"IN")) | D15: =IF($A15="","",SUMIFS('Log Transaction'!$E$4:$E$303,'Log Transaction'!$C$4:$C$303,$A15,'Log Transaction'!$D$4:$D$303,"OUT")+SUMIFS('Log Transaction'!$E$4:$E$303,'Log Transaction'!$C$4:$C$303,$A15,'Log Transaction'!$D$4:$D$303,"SHRINKAGE")) | E15: =IF($A15="","",$C15-$D15) | F15: =IF($A15="","",IF($E15<=_xlfn.XLOOKUP($A15,'Item Master'!$A$4:$A$53,'Item Master'!$F$4:$F$53,0)*0.1,"⚠️ REORDER NOW","✅ IN STOCK")) | G15: =IF($A15="","",IF($F15="⚠️ REORDER NOW",HYPERLINK("https://wa.me/"&SUBSTITUTE(SUBSTITUTE(SUBSTITUTE(SUBSTITUTE(SUBSTITUTE(SUBSTITUTE(_xlfn.XLOOKUP($A15,'Item Master'!$A$4:$A$53,'Item Master'!$I$4:$I$53,""),"+",""),"-","")," ",""),"(",""),")",""),".","")&"?text="&SUBSTITUTE("Hello "&_xlfn.XLOOKUP($A15,'Item Master'!$A$4:$A$53,'Item Master'!$H$4:$H$53,"Supplier")&", we urgently need more "&$B15&". Current stock is only "&TEXT($E15,"0")&" units. Please confirm availability and your fastest lead time. Thank you - Momentum Mind Store."," ","%20"),"💬 ORDER NOW"),"")) | H15: =IF($A15="","",IF($F15="⚠️ REORDER NOW",HYPERLINK("mailto:"&_xlfn.XLOOKUP($A15,'Item Master'!$A$4:$A$53,'Item Master'!$J$4:$J$53,"")&"?subject="&SUBSTITUTE("URGENT restock request - "&$B15&" ("&$A15&")"," ","%20")&"&body="&SUBSTITUTE(SUBSTITUTE("Hello "&_xlfn.XLOOKUP($A15,'Item Master'!$A$4:$A$53,'Item Master'!$H$4:$H$53,"Supplier")&"," & CHAR(10) & "We urgently need to restock "&$B15&" (SKU "&$A15&"). Our current stock is "&TEXT($E15,"0")&" units, which is below our reorder threshold." & CHAR(10) & "Please confirm availability, unit price and lead time by return." & CHAR(10) & "Kind regards," & CHAR(10) & "Momentum Mind Store"," ","%20"),CHAR(10),"%0D%0A"),"✉️ EMAIL"),"")) | I15: =IF($A15="","",$E15*_xlfn.XLOOKUP($A15,'Item Master'!$A$4:$A$53,'Item Master'!$D$4:$D$53,0))
A16: =IF(INDEX('Item Master'!$A$4:$A$53,8)="","",INDEX('Item Master'!$A$4:$A$53,8)) | B16: =IF($A16="","",_xlfn.XLOOKUP($A16,'Item Master'!$A$4:$A$53,'Item Master'!$B$4:$B$53,"")) | C16: =IF($A16="","",SUMIFS('Log Transaction'!$E$4:$E$303,'Log Transaction'!$C$4:$C$303,$A16,'Log Transaction'!$D$4:$D$303,"IN")) | D16: =IF($A16="","",SUMIFS('Log Transaction'!$E$4:$E$303,'Log Transaction'!$C$4:$C$303,$A16,'Log Transaction'!$D$4:$D$303,"OUT")+SUMIFS('Log Transaction'!$E$4:$E$303,'Log Transaction'!$C$4:$C$303,$A16,'Log Transaction'!$D$4:$D$303,"SHRINKAGE")) | E16: =IF($A16="","",$C16-$D16) | F16: =IF($A16="","",IF($E16<=_xlfn.XLOOKUP($A16,'Item Master'!$A$4:$A$53,'Item Master'!$F$4:$F$53,0)*0.1,"⚠️ REORDER NOW","✅ IN STOCK")) | G16: =IF($A16="","",IF($F16="⚠️ REORDER NOW",HYPERLINK("https://wa.me/"&SUBSTITUTE(SUBSTITUTE(SUBSTITUTE(SUBSTITUTE(SUBSTITUTE(SUBSTITUTE(_xlfn.XLOOKUP($A16,'Item Master'!$A$4:$A$53,'Item Master'!$I$4:$I$53,""),"+",""),"-","")," ",""),"(",""),")",""),".","")&"?text="&SUBSTITUTE("Hello "&_xlfn.XLOOKUP($A16,'Item Master'!$A$4:$A$53,'Item Master'!$H$4:$H$53,"Supplier")&", we urgently need more "&$B16&". Current stock is only "&TEXT($E16,"0")&" units. Please confirm availability and your fastest lead time. Thank you - Momentum Mind Store."," ","%20"),"💬 ORDER NOW"),"")) | H16: =IF($A16="","",IF($F16="⚠️ REORDER NOW",HYPERLINK("mailto:"&_xlfn.XLOOKUP($A16,'Item Master'!$A$4:$A$53,'Item Master'!$J$4:$J$53,"")&"?subject="&SUBSTITUTE("URGENT restock request - "&$B16&" ("&$A16&")"," ","%20")&"&body="&SUBSTITUTE(SUBSTITUTE("Hello "&_xlfn.XLOOKUP($A16,'Item Master'!$A$4:$A$53,'Item Master'!$H$4:$H$53,"Supplier")&"," & CHAR(10) & "We urgently need to restock "&$B16&" (SKU "&$A16&"). Our current stock is "&TEXT($E16,"0")&" units, which is below our reorder threshold." & CHAR(10) & "Please confirm availability, unit price and lead time by return." & CHAR(10) & "Kind regards," & CHAR(10) & "Momentum Mind Store"," ","%20"),CHAR(10),"%0D%0A"),"✉️ EMAIL"),"")) | I16: =IF($A16="","",$E16*_xlfn.XLOOKUP($A16,'Item Master'!$A$4:$A$53,'Item Master'!$D$4:$D$53,0))
A17: =IF(INDEX('Item Master'!$A$4:$A$53,9)="","",INDEX('Item Master'!$A$4:$A$53,9)) | B17: =IF($A17="","",_xlfn.XLOOKUP($A17,'Item Master'!$A$4:$A$53,'Item Master'!$B$4:$B$53,"")) | C17: =IF($A17="","",SUMIFS('Log Transaction'!$E$4:$E$303,'Log Transaction'!$C$4:$C$303,$A17,'Log Transaction'!$D$4:$D$303,"IN")) | D17: =IF($A17="","",SUMIFS('Log Transaction'!$E$4:$E$303,'Log Transaction'!$C$4:$C$303,$A17,'Log Transaction'!$D$4:$D$303,"OUT")+SUMIFS('Log Transaction'!$E$4:$E$303,'Log Transaction'!$C$4:$C$303,$A17,'Log Transaction'!$D$4:$D$303,"SHRINKAGE")) | E17: =IF($A17="","",$C17-$D17) | F17: =IF($A17="","",IF($E17<=_xlfn.XLOOKUP($A17,'Item Master'!$A$4:$A$53,'Item Master'!$F$4:$F$53,0)*0.1,"⚠️ REORDER NOW","✅ IN STOCK")) | G17: =IF($A17="","",IF($F17="⚠️ REORDER NOW",HYPERLINK("https://wa.me/"&SUBSTITUTE(SUBSTITUTE(SUBSTITUTE(SUBSTITUTE(SUBSTITUTE(SUBSTITUTE(_xlfn.XLOOKUP($A17,'Item Master'!$A$4:$A$53,'Item Master'!$I$4:$I$53,""),"+",""),"-","")," ",""),"(",""),")",""),".","")&"?text="&SUBSTITUTE("Hello "&_xlfn.XLOOKUP($A17,'Item Master'!$A$4:$A$53,'Item Master'!$H$4:$H$53,"Supplier")&", we urgently need more "&$B17&". Current stock is only "&TEXT($E17,"0")&" units. Please confirm availability and your fastest lead time. Thank you - Momentum Mind Store."," ","%20"),"💬 ORDER NOW"),"")) | H17: =IF($A17="","",IF($F17="⚠️ REORDER NOW",HYPERLINK("mailto:"&_xlfn.XLOOKUP($A17,'Item Master'!$A$4:$A$53,'Item Master'!$J$4:$J$53,"")&"?subject="&SUBSTITUTE("URGENT restock request - "&$B17&" ("&$A17&")"," ","%20")&"&body="&SUBSTITUTE(SUBSTITUTE("Hello "&_xlfn.XLOOKUP($A17,'Item Master'!$A$4:$A$53,'Item Master'!$H$4:$H$53,"Supplier")&"," & CHAR(10) & "We urgently need to restock "&$B17&" (SKU "&$A17&"). Our current stock is "&TEXT($E17,"0")&" units, which is below our reorder threshold." & CHAR(10) & "Please confirm availability, unit price and lead time by return." & CHAR(10) & "Kind regards," & CHAR(10) & "Momentum Mind Store"," ","%20"),CHAR(10),"%0D%0A"),"✉️ EMAIL"),"")) | I17: =IF($A17="","",$E17*_xlfn.XLOOKUP($A17,'Item Master'!$A$4:$A$53,'Item Master'!$D$4:$D$53,0))
A18: =IF(INDEX('Item Master'!$A$4:$A$53,10)="","",INDEX('Item Master'!$A$4:$A$53,10)) | B18: =IF($A18="","",_xlfn.XLOOKUP($A18,'Item Master'!$A$4:$A$53,'Item Master'!$B$4:$B$53,"")) | C18: =IF($A18="","",SUMIFS('Log Transaction'!$E$4:$E$303,'Log Transaction'!$C$4:$C$303,$A18,'Log Transaction'!$D$4:$D$303,"IN")) | D18: =IF($A18="","",SUMIFS('Log Transaction'!$E$4:$E$303,'Log Transaction'!$C$4:$C$303,$A18,'Log Transaction'!$D$4:$D$303,"OUT")+SUMIFS('Log Transaction'!$E$4:$E$303,'Log Transaction'!$C$4:$C$303,$A18,'Log Transaction'!$D$4:$D$303,"SHRINKAGE")) | E18: =IF($A18="","",$C18-$D18) | F18: =IF($A18="","",IF($E18<=_xlfn.XLOOKUP($A18,'Item Master'!$A$4:$A$53,'Item Master'!$F$4:$F$53,0)*0.1,"⚠️ REORDER NOW","✅ IN STOCK")) | G18: =IF($A18="","",IF($F18="⚠️ REORDER NOW",HYPERLINK("https://wa.me/"&SUBSTITUTE(SUBSTITUTE(SUBSTITUTE(SUBSTITUTE(SUBSTITUTE(SUBSTITUTE(_xlfn.XLOOKUP($A18,'Item Master'!$A$4:$A$53,'Item Master'!$I$4:$I$53,""),"+",""),"-","")," ",""),"(",""),")",""),".","")&"?text="&SUBSTITUTE("Hello "&_xlfn.XLOOKUP($A18,'Item Master'!$A$4:$A$53,'Item Master'!$H$4:$H$53,"Supplier")&", we urgently need more "&$B18&". Current stock is only "&TEXT($E18,"0")&" units. Please confirm availability and your fastest lead time. Thank you - Momentum Mind Store."," ","%20"),"💬 ORDER NOW"),"")) | H18: =IF($A18="","",IF($F18="⚠️ REORDER NOW",HYPERLINK("mailto:"&_xlfn.XLOOKUP($A18,'Item Master'!$A$4:$A$53,'Item Master'!$J$4:$J$53,"")&"?subject="&SUBSTITUTE("URGENT restock request - "&$B18&" ("&$A18&")"," ","%20")&"&body="&SUBSTITUTE(SUBSTITUTE("Hello "&_xlfn.XLOOKUP($A18,'Item Master'!$A$4:$A$53,'Item Master'!$H$4:$H$53,"Supplier")&"," & CHAR(10) & "We urgently need to restock "&$B18&" (SKU "&$A18&"). Our current stock is "&TEXT($E18,"0")&" units, which is below our reorder threshold." & CHAR(10) & "Please confirm availability, unit price and lead time by return." & CHAR(10) & "Kind regards," & CHAR(10) & "Momentum Mind Store"," ","%20"),CHAR(10),"%0D%0A"),"✉️ EMAIL"),"")) | I18: =IF($A18="","",$E18*_xlfn.XLOOKUP($A18,'Item Master'!$A$4:$A$53,'Item Master'!$D$4:$D$53,0))
A19: =IF(INDEX('Item Master'!$A$4:$A$53,11)="","",INDEX('Item Master'!$A$4:$A$53,11)) | B19: =IF($A19="","",_xlfn.XLOOKUP($A19,'Item Master'!$A$4:$A$53,'Item Master'!$B$4:$B$53,"")) | C19: =IF($A19="","",SUMIFS('Log Transaction'!$E$4:$E$303,'Log Transaction'!$C$4:$C$303,$A19,'Log Transaction'!$D$4:$D$303,"IN")) | D19: =IF($A19="","",SUMIFS('Log Transaction'!$E$4:$E$303,'Log Transaction'!$C$4:$C$303,$A19,'Log Transaction'!$D$4:$D$303,"OUT")+SUMIFS('Log Transaction'!$E$4:$E$303,'Log Transaction'!$C$4:$C$303,$A19,'Log Transaction'!$D$4:$D$303,"SHRINKAGE")) | E19: =IF($A19="","",$C19-$D19) | F19: =IF($A19="","",IF($E19<=_xlfn.XLOOKUP($A19,'Item Master'!$A$4:$A$53,'Item Master'!$F$4:$F$53,0)*0.1,"⚠️ REORDER NOW","✅ IN STOCK")) | G19: =IF($A19="","",IF($F19="⚠️ REORDER NOW",HYPERLINK("https://wa.me/"&SUBSTITUTE(SUBSTITUTE(SUBSTITUTE(SUBSTITUTE(SUBSTITUTE(SUBSTITUTE(_xlfn.XLOOKUP($A19,'Item Master'!$A$4:$A$53,'Item Master'!$I$4:$I$53,""),"+",""),"-","")," ",""),"(",""),")",""),".","")&"?text="&SUBSTITUTE("Hello "&_xlfn.XLOOKUP($A19,'Item Master'!$A$4:$A$53,'Item Master'!$H$4:$H$53,"Supplier")&", we urgently need more "&$B19&". Current stock is only "&TEXT($E19,"0")&" units. Please confirm availability and your fastest lead time. Thank you - Momentum Mind Store."," ","%20"),"💬 ORDER NOW"),"")) | H19: =IF($A19="","",IF($F19="⚠️ REORDER NOW",HYPERLINK("mailto:"&_xlfn.XLOOKUP($A19,'Item Master'!$A$4:$A$53,'Item Master'!$J$4:$J$53,"")&"?subject="&SUBSTITUTE("URGENT restock request - "&$B19&" ("&$A19&")"," ","%20")&"&body="&SUBSTITUTE(SUBSTITUTE("Hello "&_xlfn.XLOOKUP($A19,'Item Master'!$A$4:$A$53,'Item Master'!$H$4:$H$53,"Supplier")&"," & CHAR(10) & "We urgently need to restock "&$B19&" (SKU "&$A19&"). Our current stock is "&TEXT($E19,"0")&" units, which is below our reorder threshold." & CHAR(10) & "Please confirm availability, unit price and lead time by return." & CHAR(10) & "Kind regards," & CHAR(10) & "Momentum Mind Store"," ","%20"),CHAR(10),"%0D%0A"),"✉️ EMAIL"),"")) | I19: =IF($A19="","",$E19*_xlfn.XLOOKUP($A19,'Item Master'!$A$4:$A$53,'Item Master'!$D$4:$D$53,0))
A20: =IF(INDEX('Item Master'!$A$4:$A$53,12)="","",INDEX('Item Master'!$A$4:$A$53,12)) | B20: =IF($A20="","",_xlfn.XLOOKUP($A20,'Item Master'!$A$4:$A$53,'Item Master'!$B$4:$B$53,"")) | C20: =IF($A20="","",SUMIFS('Log Transaction'!$E$4:$E$303,'Log Transaction'!$C$4:$C$303,$A20,'Log Transaction'!$D$4:$D$303,"IN")) | D20: =IF($A20="","",SUMIFS('Log Transaction'!$E$4:$E$303,'Log Transaction'!$C$4:$C$303,$A20,'Log Transaction'!$D$4:$D$303,"OUT")+SUMIFS('Log Transaction'!$E$4:$E$303,'Log Transaction'!$C$4:$C$303,$A20,'Log Transaction'!$D$4:$D$303,"SHRINKAGE")) | E20: =IF($A20="","",$C20-$D20) | F20: =IF($A20="","",IF($E20<=_xlfn.XLOOKUP($A20,'Item Master'!$A$4:$A$53,'Item Master'!$F$4:$F$53,0)*0.1,"⚠️ REORDER NOW","✅ IN STOCK")) | G20: =IF($A20="","",IF($F20="⚠️ REORDER NOW",HYPERLINK("https://wa.me/"&SUBSTITUTE(SUBSTITUTE(SUBSTITUTE(SUBSTITUTE(SUBSTITUTE(SUBSTITUTE(_xlfn.XLOOKUP($A20,'Item Master'!$A$4:$A$53,'Item Master'!$I$4:$I$53,""),"+",""),"-","")," ",""),"(",""),")",""),".","")&"?text="&SUBSTITUTE("Hello "&_xlfn.XLOOKUP($A20,'Item Master'!$A$4:$A$53,'Item Master'!$H$4:$H$53,"Supplier")&", we urgently need more "&$B20&". Current stock is only "&TEXT($E20,"0")&" units. Please confirm availability and your fastest lead time. Thank you - Momentum Mind Store."," ","%20"),"💬 ORDER NOW"),"")) | H20: =IF($A20="","",IF($F20="⚠️ REORDER NOW",HYPERLINK("mailto:"&_xlfn.XLOOKUP($A20,'Item Master'!$A$4:$A$53,'Item Master'!$J$4:$J$53,"")&"?subject="&SUBSTITUTE("URGENT restock request - "&$B20&" ("&$A20&")"," ","%20")&"&body="&SUBSTITUTE(SUBSTITUTE("Hello "&_xlfn.XLOOKUP($A20,'Item Master'!$A$4:$A$53,'Item Master'!$H$4:$H$53,"Supplier")&"," & CHAR(10) & "We urgently need to restock "&$B20&" (SKU "&$A20&"). Our current stock is "&TEXT($E20,"0")&" units, which is below our reorder threshold." & CHAR(10) & "Please confirm availability, unit price and lead time by return." & CHAR(10) & "Kind regards," & CHAR(10) & "Momentum Mind Store"," ","%20"),CHAR(10),"%0D%0A"),"✉️ EMAIL"),"")) | I20: =IF($A20="","",$E20*_xlfn.XLOOKUP($A20,'Item Master'!$A$4:$A$53,'Item Master'!$D$4:$D$53,0))
A21: =IF(INDEX('Item Master'!$A$4:$A$53,13)="","",INDEX('Item Master'!$A$4:$A$53,13)) | B21: =IF($A21="","",_xlfn.XLOOKUP($A21,'Item Master'!$A$4:$A$53,'Item Master'!$B$4:$B$53,"")) | C21: =IF($A21="","",SUMIFS('Log Transaction'!$E$4:$E$303,'Log Transaction'!$C$4:$C$303,$A21,'Log Transaction'!$D$4:$D$303,"IN")) | D21: =IF($A21="","",SUMIFS('Log Transaction'!$E$4:$E$303,'Log Transaction'!$C$4:$C$303,$A21,'Log Transaction'!$D$4:$D$303,"OUT")+SUMIFS('Log Transaction'!$E$4:$E$303,'Log Transaction'!$C$4:$C$303,$A21,'Log Transaction'!$D$4:$D$303,"SHRINKAGE")) | E21: =IF($A21="","",$C21-$D21) | F21: =IF($A21="","",IF($E21<=_xlfn.XLOOKUP($A21,'Item Master'!$A$4:$A$53,'Item Master'!$F$4:$F$53,0)*0.1,"⚠️ REORDER NOW","✅ IN STOCK")) | G21: =IF($A21="","",IF($F21="⚠️ REORDER NOW",HYPERLINK("https://wa.me/"&SUBSTITUTE(SUBSTITUTE(SUBSTITUTE(SUBSTITUTE(SUBSTITUTE(SUBSTITUTE(_xlfn.XLOOKUP($A21,'Item Master'!$A$4:$A$53,'Item Master'!$I$4:$I$53,""),"+",""),"-","")," ",""),"(",""),")",""),".","")&"?text="&SUBSTITUTE("Hello "&_xlfn.XLOOKUP($A21,'Item Master'!$A$4:$A$53,'Item Master'!$H$4:$H$53,"Supplier")&", we urgently need more "&$B21&". Current stock is only "&TEXT($E21,"0")&" units. Please confirm availability and your fastest lead time. Thank you - Momentum Mind Store."," ","%20"),"💬 ORDER NOW"),"")) | H21: =IF($A21="","",IF($F21="⚠️ REORDER NOW",HYPERLINK("mailto:"&_xlfn.XLOOKUP($A21,'Item Master'!$A$4:$A$53,'Item Master'!$J$4:$J$53,"")&"?subject="&SUBSTITUTE("URGENT restock request - "&$B21&" ("&$A21&")"," ","%20")&"&body="&SUBSTITUTE(SUBSTITUTE("Hello "&_xlfn.XLOOKUP($A21,'Item Master'!$A$4:$A$53,'Item Master'!$H$4:$H$53,"Supplier")&"," & CHAR(10) & "We urgently need to restock "&$B21&" (SKU "&$A21&"). Our current stock is "&TEXT($E21,"0")&" units, which is below our reorder threshold." & CHAR(10) & "Please confirm availability, unit price and lead time by return." & CHAR(10) & "Kind regards," & CHAR(10) & "Momentum Mind Store"," ","%20"),CHAR(10),"%0D%0A"),"✉️ EMAIL"),"")) | I21: =IF($A21="","",$E21*_xlfn.XLOOKUP($A21,'Item Master'!$A$4:$A$53,'Item Master'!$D$4:$D$53,0))
A22: =IF(INDEX('Item Master'!$A$4:$A$53,14)="","",INDEX('Item Master'!$A$4:$A$53,14)) | B22: =IF($A22="","",_xlfn.XLOOKUP($A22,'Item Master'!$A$4:$A$53,'Item Master'!$B$4:$B$53,"")) | C22: =IF($A22="","",SUMIFS('Log Transaction'!$E$4:$E$303,'Log Transaction'!$C$4:$C$303,$A22,'Log Transaction'!$D$4:$D$303,"IN")) | D22: =IF($A22="","",SUMIFS('Log Transaction'!$E$4:$E$303,'Log Transaction'!$C$4:$C$303,$A22,'Log Transaction'!$D$4:$D$303,"OUT")+SUMIFS('Log Transaction'!$E$4:$E$303,'Log Transaction'!$C$4:$C$303,$A22,'Log Transaction'!$D$4:$D$303,"SHRINKAGE")) | E22: =IF($A22="","",$C22-$D22) | F22: =IF($A22="","",IF($E22<=_xlfn.XLOOKUP($A22,'Item Master'!$A$4:$A$53,'Item Master'!$F$4:$F$53,0)*0.1,"⚠️ REORDER NOW","✅ IN STOCK")) | G22: =IF($A22="","",IF($F22="⚠️ REORDER NOW",HYPERLINK("https://wa.me/"&SUBSTITUTE(SUBSTITUTE(SUBSTITUTE(SUBSTITUTE(SUBSTITUTE(SUBSTITUTE(_xlfn.XLOOKUP($A22,'Item Master'!$A$4:$A$53,'Item Master'!$I$4:$I$53,""),"+",""),"-","")," ",""),"(",""),")",""),".","")&"?text="&SUBSTITUTE("Hello "&_xlfn.XLOOKUP($A22,'Item Master'!$A$4:$A$53,'Item Master'!$H$4:$H$53,"Supplier")&", we urgently need more "&$B22&". Current stock is only "&TEXT($E22,"0")&" units. Please confirm availability and your fastest lead time. Thank you - Momentum Mind Store."," ","%20"),"💬 ORDER NOW"),"")) | H22: =IF($A22="","",IF($F22="⚠️ REORDER NOW",HYPERLINK("mailto:"&_xlfn.XLOOKUP($A22,'Item Master'!$A$4:$A$53,'Item Master'!$J$4:$J$53,"")&"?subject="&SUBSTITUTE("URGENT restock request - "&$B22&" ("&$A22&")"," ","%20")&"&body="&SUBSTITUTE(SUBSTITUTE("Hello "&_xlfn.XLOOKUP($A22,'Item Master'!$A$4:$A$53,'Item Master'!$H$4:$H$53,"Supplier")&"," & CHAR(10) & "We urgently need to restock "&$B22&" (SKU "&$A22&"). Our current stock is "&TEXT($E22,"0")&" units, which is below our reorder threshold." & CHAR(10) & "Please confirm availability, unit price and lead time by return." & CHAR(10) & "Kind regards," & CHAR(10) & "Momentum Mind Store"," ","%20"),CHAR(10),"%0D%0A"),"✉️ EMAIL"),"")) | I22: =IF($A22="","",$E22*_xlfn.XLOOKUP($A22,'Item Master'!$A$4:$A$53,'Item Master'!$D$4:$D$53,0))
A23: =IF(INDEX('Item Master'!$A$4:$A$53,15)="","",INDEX('Item Master'!$A$4:$A$53,15)) | B23: =IF($A23="","",_xlfn.XLOOKUP($A23,'Item Master'!$A$4:$A$53,'Item Master'!$B$4:$B$53,"")) | C23: =IF($A23="","",SUMIFS('Log Transaction'!$E$4:$E$303,'Log Transaction'!$C$4:$C$303,$A23,'Log Transaction'!$D$4:$D$303,"IN")) | D23: =IF($A23="","",SUMIFS('Log Transaction'!$E$4:$E$303,'Log Transaction'!$C$4:$C$303,$A23,'Log Transaction'!$D$4:$D$303,"OUT")+SUMIFS('Log Transaction'!$E$4:$E$303,'Log Transaction'!$C$4:$C$303,$A23,'Log Transaction'!$D$4:$D$303,"SHRINKAGE")) | E23: =IF($A23="","",$C23-$D23) | F23: =IF($A23="","",IF($E23<=_xlfn.XLOOKUP($A23,'Item Master'!$A$4:$A$53,'Item Master'!$F$4:$F$53,0)*0.1,"⚠️ REORDER NOW","✅ IN STOCK")) | G23: =IF($A23="","",IF($F23="⚠️ REORDER NOW",HYPERLINK("https://wa.me/"&SUBSTITUTE(SUBSTITUTE(SUBSTITUTE(SUBSTITUTE(SUBSTITUTE(SUBSTITUTE(_xlfn.XLOOKUP($A23,'Item Master'!$A$4:$A$53,'Item Master'!$I$4:$I$53,""),"+",""),"-","")," ",""),"(",""),")",""),".","")&"?text="&SUBSTITUTE("Hello "&_xlfn.XLOOKUP($A23,'Item Master'!$A$4:$A$53,'Item Master'!$H$4:$H$53,"Supplier")&", we urgently need more "&$B23&". Current stock is only "&TEXT($E23,"0")&" units. Please confirm availability and your fastest lead time. Thank you - Momentum Mind Store."," ","%20"),"💬 ORDER NOW"),"")) | H23: =IF($A23="","",IF($F23="⚠️ REORDER NOW",HYPERLINK("mailto:"&_xlfn.XLOOKUP($A23,'Item Master'!$A$4:$A$53,'Item Master'!$J$4:$J$53,"")&"?subject="&SUBSTITUTE("URGENT restock request - "&$B23&" ("&$A23&")"," ","%20")&"&body="&SUBSTITUTE(SUBSTITUTE("Hello "&_xlfn.XLOOKUP($A23,'Item Master'!$A$4:$A$53,'Item Master'!$H$4:$H$53,"Supplier")&"," & CHAR(10) & "We urgently need to restock "&$B23&" (SKU "&$A23&"). Our current stock is "&TEXT($E23,"0")&" units, which is below our reorder threshold." & CHAR(10) & "Please confirm availability, unit price and lead time by return." & CHAR(10) & "Kind regards," & CHAR(10) & "Momentum Mind Store"," ","%20"),CHAR(10),"%0D%0A"),"✉️ EMAIL"),"")) | I23: =IF($A23="","",$E23*_xlfn.XLOOKUP($A23,'Item Master'!$A$4:$A$53,'Item Master'!$D$4:$D$53,0))
A24: =IF(INDEX('Item Master'!$A$4:$A$53,16)="","",INDEX('Item Master'!$A$4:$A$53,16)) | B24: =IF($A24="","",_xlfn.XLOOKUP($A24,'Item Master'!$A$4:$A$53,'Item Master'!$B$4:$B$53,"")) | C24: =IF($A24="","",SUMIFS('Log Transaction'!$E$4:$E$303,'Log Transaction'!$C$4:$C$303,$A24,'Log Transaction'!$D$4:$D$303,"IN")) | D24: =IF($A24="","",SUMIFS('Log Transaction'!$E$4:$E$303,'Log Transaction'!$C$4:$C$303,$A24,'Log Transaction'!$D$4:$D$303,"OUT")+SUMIFS('Log Transaction'!$E$4:$E$303,'Log Transaction'!$C$4:$C$303,$A24,'Log Transaction'!$D$4:$D$303,"SHRINKAGE")) | E24: =IF($A24="","",$C24-$D24) | F24: =IF($A24="","",IF($E24<=_xlfn.XLOOKUP($A24,'Item Master'!$A$4:$A$53,'Item Master'!$F$4:$F$53,0)*0.1,"⚠️ REORDER NOW","✅ IN STOCK")) | G24: =IF($A24="","",IF($F24="⚠️ REORDER NOW",HYPERLINK("https://wa.me/"&SUBSTITUTE(SUBSTITUTE(SUBSTITUTE(SUBSTITUTE(SUBSTITUTE(SUBSTITUTE(_xlfn.XLOOKUP($A24,'Item Master'!$A$4:$A$53,'Item Master'!$I$4:$I$53,""),"+",""),"-","")," ",""),"(",""),")",""),".","")&"?text="&SUBSTITUTE("Hello "&_xlfn.XLOOKUP($A24,'Item Master'!$A$4:$A$53,'Item Master'!$H$4:$H$53,"Supplier")&", we urgently need more "&$B24&". Current stock is only "&TEXT($E24,"0")&" units. Please confirm availability and your fastest lead time. Thank you - Momentum Mind Store."," ","%20"),"💬 ORDER NOW"),"")) | H24: =IF($A24="","",IF($F24="⚠️ REORDER NOW",HYPERLINK("mailto:"&_xlfn.XLOOKUP($A24,'Item Master'!$A$4:$A$53,'Item Master'!$J$4:$J$53,"")&"?subject="&SUBSTITUTE("URGENT restock request - "&$B24&" ("&$A24&")"," ","%20")&"&body="&SUBSTITUTE(SUBSTITUTE("Hello "&_xlfn.XLOOKUP($A24,'Item Master'!$A$4:$A$53,'Item Master'!$H$4:$H$53,"Supplier")&"," & CHAR(10) & "We urgently need to restock "&$B24&" (SKU "&$A24&"). Our current stock is "&TEXT($E24,"0")&" units, which is below our reorder threshold." & CHAR(10) & "Please confirm availability, unit price and lead time by return." & CHAR(10) & "Kind regards," & CHAR(10) & "Momentum Mind Store"," ","%20"),CHAR(10),"%0D%0A"),"✉️ EMAIL"),"")) | I24: =IF($A24="","",$E24*_xlfn.XLOOKUP($A24,'Item Master'!$A$4:$A$53,'Item Master'!$D$4:$D$53,0))
A25: =IF(INDEX('Item Master'!$A$4:$A$53,17)="","",INDEX('Item Master'!$A$4:$A$53,17)) | B25: =IF($A25="","",_xlfn.XLOOKUP($A25,'Item Master'!$A$4:$A$53,'Item Master'!$B$4:$B$53,"")) | C25: =IF($A25="","",SUMIFS('Log Transaction'!$E$4:$E$303,'Log Transaction'!$C$4:$C$303,$A25,'Log Transaction'!$D$4:$D$303,"IN")) | D25: =IF($A25="","",SUMIFS('Log Transaction'!$E$4:$E$303,'Log Transaction'!$C$4:$C$303,$A25,'Log Transaction'!$D$4:$D$303,"OUT")+SUMIFS('Log Transaction'!$E$4:$E$303,'Log Transaction'!$C$4:$C$303,$A25,'Log Transaction'!$D$4:$D$303,"SHRINKAGE")) | E25: =IF($A25="","",$C25-$D25) | F25: =IF($A25="","",IF($E25<=_xlfn.XLOOKUP($A25,'Item Master'!$A$4:$A$53,'Item Master'!$F$4:$F$53,0)*0.1,"⚠️ REORDER NOW","✅ IN STOCK")) | G25: =IF($A25="","",IF($F25="⚠️ REORDER NOW",HYPERLINK("https://wa.me/"&SUBSTITUTE(SUBSTITUTE(SUBSTITUTE(SUBSTITUTE(SUBSTITUTE(SUBSTITUTE(_xlfn.XLOOKUP($A25,'Item Master'!$A$4:$A$53,'Item Master'!$I$4:$I$53,""),"+",""),"-","")," ",""),"(",""),")",""),".","")&"?text="&SUBSTITUTE("Hello "&_xlfn.XLOOKUP($A25,'Item Master'!$A$4:$A$53,'Item Master'!$H$4:$H$53,"Supplier")&", we urgently need more "&$B25&". Current stock is only "&TEXT($E25,"0")&" units. Please confirm availability and your fastest lead time. Thank you - Momentum Mind Store."," ","%20"),"💬 ORDER NOW"),"")) | H25: =IF($A25="","",IF($F25="⚠️ REORDER NOW",HYPERLINK("mailto:"&_xlfn.XLOOKUP($A25,'Item Master'!$A$4:$A$53,'Item Master'!$J$4:$J$53,"")&"?subject="&SUBSTITUTE("URGENT restock request - "&$B25&" ("&$A25&")"," ","%20")&"&body="&SUBSTITUTE(SUBSTITUTE("Hello "&_xlfn.XLOOKUP($A25,'Item Master'!$A$4:$A$53,'Item Master'!$H$4:$H$53,"Supplier")&"," & CHAR(10) & "We urgently need to restock "&$B25&" (SKU "&$A25&"). Our current stock is "&TEXT($E25,"0")&" units, which is below our reorder threshold." & CHAR(10) & "Please confirm availability, unit price and lead time by return." & CHAR(10) & "Kind regards," & CHAR(10) & "Momentum Mind Store"," ","%20"),CHAR(10),"%0D%0A"),"✉️ EMAIL"),"")) | I25: =IF($A25="","",$E25*_xlfn.XLOOKUP($A25,'Item Master'!$A$4:$A$53,'Item Master'!$D$4:$D$53,0))
A26: =IF(INDEX('Item Master'!$A$4:$A$53,18)="","",INDEX('Item Master'!$A$4:$A$53,18)) | B26: =IF($A26="","",_xlfn.XLOOKUP($A26,'Item Master'!$A$4:$A$53,'Item Master'!$B$4:$B$53,"")) | C26: =IF($A26="","",SUMIFS('Log Transaction'!$E$4:$E$303,'Log Transaction'!$C$4:$C$303,$A26,'Log Transaction'!$D$4:$D$303,"IN")) | D26: =IF($A26="","",SUMIFS('Log Transaction'!$E$4:$E$303,'Log Transaction'!$C$4:$C$303,$A26,'Log Transaction'!$D$4:$D$303,"OUT")+SUMIFS('Log Transaction'!$E$4:$E$303,'Log Transaction'!$C$4:$C$303,$A26,'Log Transaction'!$D$4:$D$303,"SHRINKAGE")) | E26: =IF($A26="","",$C26-$D26) | F26: =IF($A26="","",IF($E26<=_xlfn.XLOOKUP($A26,'Item Master'!$A$4:$A$53,'Item Master'!$F$4:$F$53,0)*0.1,"⚠️ REORDER NOW","✅ IN STOCK")) | G26: =IF($A26="","",IF($F26="⚠️ REORDER NOW",HYPERLINK("https://wa.me/"&SUBSTITUTE(SUBSTITUTE(SUBSTITUTE(SUBSTITUTE(SUBSTITUTE(SUBSTITUTE(_xlfn.XLOOKUP($A26,'Item Master'!$A$4:$A$53,'Item Master'!$I$4:$I$53,""),"+",""),"-","")," ",""),"(",""),")",""),".","")&"?text="&SUBSTITUTE("Hello "&_xlfn.XLOOKUP($A26,'Item Master'!$A$4:$A$53,'Item Master'!$H$4:$H$53,"Supplier")&", we urgently need more "&$B26&". Current stock is only "&TEXT($E26,"0")&" units. Please confirm availability and your fastest lead time. Thank you - Momentum Mind Store."," ","%20"),"💬 ORDER NOW"),"")) | H26: =IF($A26="","",IF($F26="⚠️ REORDER NOW",HYPERLINK("mailto:"&_xlfn.XLOOKUP($A26,'Item Master'!$A$4:$A$53,'Item Master'!$J$4:$J$53,"")&"?subject="&SUBSTITUTE("URGENT restock request - "&$B26&" ("&$A26&")"," ","%20")&"&body="&SUBSTITUTE(SUBSTITUTE("Hello "&_xlfn.XLOOKUP($A26,'Item Master'!$A$4:$A$53,'Item Master'!$H$4:$H$53,"Supplier")&"," & CHAR(10) & "We urgently need to restock "&$B26&" (SKU "&$A26&"). Our current stock is "&TEXT($E26,"0")&" units, which is below our reorder threshold." & CHAR(10) & "Please confirm availability, unit price and lead time by return." & CHAR(10) & "Kind regards," & CHAR(10) & "Momentum Mind Store"," ","%20"),CHAR(10),"%0D%0A"),"✉️ EMAIL"),"")) | I26: =IF($A26="","",$E26*_xlfn.XLOOKUP($A26,'Item Master'!$A$4:$A$53,'Item Master'!$D$4:$D$53,0))
A27: =IF(INDEX('Item Master'!$A$4:$A$53,19)="","",INDEX('Item Master'!$A$4:$A$53,19)) | B27: =IF($A27="","",_xlfn.XLOOKUP($A27,'Item Master'!$A$4:$A$53,'Item Master'!$B$4:$B$53,"")) | C27: =IF($A27="","",SUMIFS('Log Transaction'!$E$4:$E$303,'Log Transaction'!$C$4:$C$303,$A27,'Log Transaction'!$D$4:$D$303,"IN")) | D27: =IF($A27="","",SUMIFS('Log Transaction'!$E$4:$E$303,'Log Transaction'!$C$4:$C$303,$A27,'Log Transaction'!$D$4:$D$303,"OUT")+SUMIFS('Log Transaction'!$E$4:$E$303,'Log Transaction'!$C$4:$C$303,$A27,'Log Transaction'!$D$4:$D$303,"SHRINKAGE")) | E27: =IF($A27="","",$C27-$D27) | F27: =IF($A27="","",IF($E27<=_xlfn.XLOOKUP($A27,'Item Master'!$A$4:$A$53,'Item Master'!$F$4:$F$53,0)*0.1,"⚠️ REORDER NOW","✅ IN STOCK")) | G27: =IF($A27="","",IF($F27="⚠️ REORDER NOW",HYPERLINK("https://wa.me/"&SUBSTITUTE(SUBSTITUTE(SUBSTITUTE(SUBSTITUTE(SUBSTITUTE(SUBSTITUTE(_xlfn.XLOOKUP($A27,'Item Master'!$A$4:$A$53,'Item Master'!$I$4:$I$53,""),"+",""),"-","")," ",""),"(",""),")",""),".","")&"?text="&SUBSTITUTE("Hello "&_xlfn.XLOOKUP($A27,'Item Master'!$A$4:$A$53,'Item Master'!$H$4:$H$53,"Supplier")&", we urgently need more "&$B27&". Current stock is only "&TEXT($E27,"0")&" units. Please confirm availability and your fastest lead time. Thank you - Momentum Mind Store."," ","%20"),"💬 ORDER NOW"),"")) | H27: =IF($A27="","",IF($F27="⚠️ REORDER NOW",HYPERLINK("mailto:"&_xlfn.XLOOKUP($A27,'Item Master'!$A$4:$A$53,'Item Master'!$J$4:$J$53,"")&"?subject="&SUBSTITUTE("URGENT restock request - "&$B27&" ("&$A27&")"," ","%20")&"&body="&SUBSTITUTE(SUBSTITUTE("Hello "&_xlfn.XLOOKUP($A27,'Item Master'!$A$4:$A$53,'Item Master'!$H$4:$H$53,"Supplier")&"," & CHAR(10) & "We urgently need to restock "&$B27&" (SKU "&$A27&"). Our current stock is "&TEXT($E27,"0")&" units, which is below our reorder threshold." & CHAR(10) & "Please confirm availability, unit price and lead time by return." & CHAR(10) & "Kind regards," & CHAR(10) & "Momentum Mind Store"," ","%20"),CHAR(10),"%0D%0A"),"✉️ EMAIL"),"")) | I27: =IF($A27="","",$E27*_xlfn.XLOOKUP($A27,'Item Master'!$A$4:$A$53,'Item Master'!$D$4:$D$53,0))
A28: =IF(INDEX('Item Master'!$A$4:$A$53,20)="","",INDEX('Item Master'!$A$4:$A$53,20)) | B28: =IF($A28="","",_xlfn.XLOOKUP($A28,'Item Master'!$A$4:$A$53,'Item Master'!$B$4:$B$53,"")) | C28: =IF($A28="","",SUMIFS('Log Transaction'!$E$4:$E$303,'Log Transaction'!$C$4:$C$303,$A28,'Log Transaction'!$D$4:$D$303,"IN")) | D28: =IF($A28="","",SUMIFS('Log Transaction'!$E$4:$E$303,'Log Transaction'!$C$4:$C$303,$A28,'Log Transaction'!$D$4:$D$303,"OUT")+SUMIFS('Log Transaction'!$E$4:$E$303,'Log Transaction'!$C$4:$C$303,$A28,'Log Transaction'!$D$4:$D$303,"SHRINKAGE")) | E28: =IF($A28="","",$C28-$D28) | F28: =IF($A28="","",IF($E28<=_xlfn.XLOOKUP($A28,'Item Master'!$A$4:$A$53,'Item Master'!$F$4:$F$53,0)*0.1,"⚠️ REORDER NOW","✅ IN STOCK")) | G28: =IF($A28="","",IF($F28="⚠️ REORDER NOW",HYPERLINK("https://wa.me/"&SUBSTITUTE(SUBSTITUTE(SUBSTITUTE(SUBSTITUTE(SUBSTITUTE(SUBSTITUTE(_xlfn.XLOOKUP($A28,'Item Master'!$A$4:$A$53,'Item Master'!$I$4:$I$53,""),"+",""),"-","")," ",""),"(",""),")",""),".","")&"?text="&SUBSTITUTE("Hello "&_xlfn.XLOOKUP($A28,'Item Master'!$A$4:$A$53,'Item Master'!$H$4:$H$53,"Supplier")&", we urgently need more "&$B28&". Current stock is only "&TEXT($E28,"0")&" units. Please confirm availability and your fastest lead time. Thank you - Momentum Mind Store."," ","%20"),"💬 ORDER NOW"),"")) | H28: =IF($A28="","",IF($F28="⚠️ REORDER NOW",HYPERLINK("mailto:"&_xlfn.XLOOKUP($A28,'Item Master'!$A$4:$A$53,'Item Master'!$J$4:$J$53,"")&"?subject="&SUBSTITUTE("URGENT restock request - "&$B28&" ("&$A28&")"," ","%20")&"&body="&SUBSTITUTE(SUBSTITUTE("Hello "&_xlfn.XLOOKUP($A28,'Item Master'!$A$4:$A$53,'Item Master'!$H$4:$H$53,"Supplier")&"," & CHAR(10) & "We urgently need to restock "&$B28&" (SKU "&$A28&"). Our current stock is "&TEXT($E28,"0")&" units, which is below our reorder threshold." & CHAR(10) & "Please confirm availability, unit price and lead time by return." & CHAR(10) & "Kind regards," & CHAR(10) & "Momentum Mind Store"," ","%20"),CHAR(10),"%0D%0A"),"✉️ EMAIL"),"")) | I28: =IF($A28="","",$E28*_xlfn.XLOOKUP($A28,'Item Master'!$A$4:$A$53,'Item Master'!$D$4:$D$53,0))
A29: =IF(INDEX('Item Master'!$A$4:$A$53,21)="","",INDEX('Item Master'!$A$4:$A$53,21)) | B29: =IF($A29="","",_xlfn.XLOOKUP($A29,'Item Master'!$A$4:$A$53,'Item Master'!$B$4:$B$53,"")) | C29: =IF($A29="","",SUMIFS('Log Transaction'!$E$4:$E$303,'Log Transaction'!$C$4:$C$303,$A29,'Log Transaction'!$D$4:$D$303,"IN")) | D29: =IF($A29="","",SUMIFS('Log Transaction'!$E$4:$E$303,'Log Transaction'!$C$4:$C$303,$A29,'Log Transaction'!$D$4:$D$303,"OUT")+SUMIFS('Log Transaction'!$E$4:$E$303,'Log Transaction'!$C$4:$C$303,$A29,'Log Transaction'!$D$4:$D$303,"SHRINKAGE")) | E29: =IF($A29="","",$C29-$D29) | F29: =IF($A29="","",IF($E29<=_xlfn.XLOOKUP($A29,'Item Master'!$A$4:$A$53,'Item Master'!$F$4:$F$53,0)*0.1,"⚠️ REORDER NOW","✅ IN STOCK")) | G29: =IF($A29="","",IF($F29="⚠️ REORDER NOW",HYPERLINK("https://wa.me/"&SUBSTITUTE(SUBSTITUTE(SUBSTITUTE(SUBSTITUTE(SUBSTITUTE(SUBSTITUTE(_xlfn.XLOOKUP($A29,'Item Master'!$A$4:$A$53,'Item Master'!$I$4:$I$53,""),"+",""),"-","")," ",""),"(",""),")",""),".","")&"?text="&SUBSTITUTE("Hello "&_xlfn.XLOOKUP($A29,'Item Master'!$A$4:$A$53,'Item Master'!$H$4:$H$53,"Supplier")&", we urgently need more "&$B29&". Current stock is only "&TEXT($E29,"0")&" units. Please confirm availability and your fastest lead time. Thank you - Momentum Mind Store."," ","%20"),"💬 ORDER NOW"),"")) | H29: =IF($A29="","",IF($F29="⚠️ REORDER NOW",HYPERLINK("mailto:"&_xlfn.XLOOKUP($A29,'Item Master'!$A$4:$A$53,'Item Master'!$J$4:$J$53,"")&"?subject="&SUBSTITUTE("URGENT restock request - "&$B29&" ("&$A29&")"," ","%20")&"&body="&SUBSTITUTE(SUBSTITUTE("Hello "&_xlfn.XLOOKUP($A29,'Item Master'!$A$4:$A$53,'Item Master'!$H$4:$H$53,"Supplier")&"," & CHAR(10) & "We urgently need to restock "&$B29&" (SKU "&$A29&"). Our current stock is "&TEXT($E29,"0")&" units, which is below our reorder threshold." & CHAR(10) & "Please confirm availability, unit price and lead time by return." & CHAR(10) & "Kind regards," & CHAR(10) & "Momentum Mind Store"," ","%20"),CHAR(10),"%0D%0A"),"✉️ EMAIL"),"")) | I29: =IF($A29="","",$E29*_xlfn.XLOOKUP($A29,'Item Master'!$A$4:$A$53,'Item Master'!$D$4:$D$53,0))
A30: =IF(INDEX('Item Master'!$A$4:$A$53,22)="","",INDEX('Item Master'!$A$4:$A$53,22)) | B30: =IF($A30="","",_xlfn.XLOOKUP($A30,'Item Master'!$A$4:$A$53,'Item Master'!$B$4:$B$53,"")) | C30: =IF($A30="","",SUMIFS('Log Transaction'!$E$4:$E$303,'Log Transaction'!$C$4:$C$303,$A30,'Log Transaction'!$D$4:$D$303,"IN")) | D30: =IF($A30="","",SUMIFS('Log Transaction'!$E$4:$E$303,'Log Transaction'!$C$4:$C$303,$A30,'Log Transaction'!$D$4:$D$303,"OUT")+SUMIFS('Log Transaction'!$E$4:$E$303,'Log Transaction'!$C$4:$C$303,$A30,'Log Transaction'!$D$4:$D$303,"SHRINKAGE")) | E30: =IF($A30="","",$C30-$D30) | F30: =IF($A30="","",IF($E30<=_xlfn.XLOOKUP($A30,'Item Master'!$A$4:$A$53,'Item Master'!$F$4:$F$53,0)*0.1,"⚠️ REORDER NOW","✅ IN STOCK")) | G30: =IF($A30="","",IF($F30="⚠️ REORDER NOW",HYPERLINK("https://wa.me/"&SUBSTITUTE(SUBSTITUTE(SUBSTITUTE(SUBSTITUTE(SUBSTITUTE(SUBSTITUTE(_xlfn.XLOOKUP($A30,'Item Master'!$A$4:$A$53,'Item Master'!$I$4:$I$53,""),"+",""),"-","")," ",""),"(",""),")",""),".","")&"?text="&SUBSTITUTE("Hello "&_xlfn.XLOOKUP($A30,'Item Master'!$A$4:$A$53,'Item Master'!$H$4:$H$53,"Supplier")&", we urgently need more "&$B30&". Current stock is only "&TEXT($E30,"0")&" units. Please confirm availability and your fastest lead time. Thank you - Momentum Mind Store."," ","%20"),"💬 ORDER NOW"),"")) | H30: =IF($A30="","",IF($F30="⚠️ REORDER NOW",HYPERLINK("mailto:"&_xlfn.XLOOKUP($A30,'Item Master'!$A$4:$A$53,'Item Master'!$J$4:$J$53,"")&"?subject="&SUBSTITUTE("URGENT restock request - "&$B30&" ("&$A30&")"," ","%20")&"&body="&SUBSTITUTE(SUBSTITUTE("Hello "&_xlfn.XLOOKUP($A30,'Item Master'!$A$4:$A$53,'Item Master'!$H$4:$H$53,"Supplier")&"," & CHAR(10) & "We urgently need to restock "&$B30&" (SKU "&$A30&"). Our current stock is "&TEXT($E30,"0")&" units, which is below our reorder threshold." & CHAR(10) & "Please confirm availability, unit price and lead time by return." & CHAR(10) & "Kind regards," & CHAR(10) & "Momentum Mind Store"," ","%20"),CHAR(10),"%0D%0A"),"✉️ EMAIL"),"")) | I30: =IF($A30="","",$E30*_xlfn.XLOOKUP($A30,'Item Master'!$A$4:$A$53,'Item Master'!$D$4:$D$53,0))
A31: =IF(INDEX('Item Master'!$A$4:$A$53,23)="","",INDEX('Item Master'!$A$4:$A$53,23)) | B31: =IF($A31="","",_xlfn.XLOOKUP($A31,'Item Master'!$A$4:$A$53,'Item Master'!$B$4:$B$53,"")) | C31: =IF($A31="","",SUMIFS('Log Transaction'!$E$4:$E$303,'Log Transaction'!$C$4:$C$303,$A31,'Log Transaction'!$D$4:$D$303,"IN")) | D31: =IF($A31="","",SUMIFS('Log Transaction'!$E$4:$E$303,'Log Transaction'!$C$4:$C$303,$A31,'Log Transaction'!$D$4:$D$303,"OUT")+SUMIFS('Log Transaction'!$E$4:$E$303,'Log Transaction'!$C$4:$C$303,$A31,'Log Transaction'!$D$4:$D$303,"SHRINKAGE")) | E31: =IF($A31="","",$C31-$D31) | F31: =IF($A31="","",IF($E31<=_xlfn.XLOOKUP($A31,'Item Master'!$A$4:$A$53,'Item Master'!$F$4:$F$53,0)*0.1,"⚠️ REORDER NOW","✅ IN STOCK")) | G31: =IF($A31="","",IF($F31="⚠️ REORDER NOW",HYPERLINK("https://wa.me/"&SUBSTITUTE(SUBSTITUTE(SUBSTITUTE(SUBSTITUTE(SUBSTITUTE(SUBSTITUTE(_xlfn.XLOOKUP($A31,'Item Master'!$A$4:$A$53,'Item Master'!$I$4:$I$53,""),"+",""),"-","")," ",""),"(",""),")",""),".","")&"?text="&SUBSTITUTE("Hello "&_xlfn.XLOOKUP($A31,'Item Master'!$A$4:$A$53,'Item Master'!$H$4:$H$53,"Supplier")&", we urgently need more "&$B31&". Current stock is only "&TEXT($E31,"0")&" units. Please confirm availability and your fastest lead time. Thank you - Momentum Mind Store."," ","%20"),"💬 ORDER NOW"),"")) | H31: =IF($A31="","",IF($F31="⚠️ REORDER NOW",HYPERLINK("mailto:"&_xlfn.XLOOKUP($A31,'Item Master'!$A$4:$A$53,'Item Master'!$J$4:$J$53,"")&"?subject="&SUBSTITUTE("URGENT restock request - "&$B31&" ("&$A31&")"," ","%20")&"&body="&SUBSTITUTE(SUBSTITUTE("Hello "&_xlfn.XLOOKUP($A31,'Item Master'!$A$4:$A$53,'Item Master'!$H$4:$H$53,"Supplier")&"," & CHAR(10) & "We urgently need to restock "&$B31&" (SKU "&$A31&"). Our current stock is "&TEXT($E31,"0")&" units, which is below our reorder threshold." & CHAR(10) & "Please confirm availability, unit price and lead time by return." & CHAR(10) & "Kind regards," & CHAR(10) & "Momentum Mind Store"," ","%20"),CHAR(10),"%0D%0A"),"✉️ EMAIL"),"")) | I31: =IF($A31="","",$E31*_xlfn.XLOOKUP($A31,'Item Master'!$A$4:$A$53,'Item Master'!$D$4:$D$53,0))
A32: =IF(INDEX('Item Master'!$A$4:$A$53,24)="","",INDEX('Item Master'!$A$4:$A$53,24)) | B32: =IF($A32="","",_xlfn.XLOOKUP($A32,'Item Master'!$A$4:$A$53,'Item Master'!$B$4:$B$53,"")) | C32: =IF($A32="","",SUMIFS('Log Transaction'!$E$4:$E$303,'Log Transaction'!$C$4:$C$303,$A32,'Log Transaction'!$D$4:$D$303,"IN")) | D32: =IF($A32="","",SUMIFS('Log Transaction'!$E$4:$E$303,'Log Transaction'!$C$4:$C$303,$A32,'Log Transaction'!$D$4:$D$303,"OUT")+SUMIFS('Log Transaction'!$E$4:$E$303,'Log Transaction'!$C$4:$C$303,$A32,'Log Transaction'!$D$4:$D$303,"SHRINKAGE")) | E32: =IF($A32="","",$C32-$D32) | F32: =IF($A32="","",IF($E32<=_xlfn.XLOOKUP($A32,'Item Master'!$A$4:$A$53,'Item Master'!$F$4:$F$53,0)*0.1,"⚠️ REORDER NOW","✅ IN STOCK")) | G32: =IF($A32="","",IF($F32="⚠️ REORDER NOW",HYPERLINK("https://wa.me/"&SUBSTITUTE(SUBSTITUTE(SUBSTITUTE(SUBSTITUTE(SUBSTITUTE(SUBSTITUTE(_xlfn.XLOOKUP($A32,'Item Master'!$A$4:$A$53,'Item Master'!$I$4:$I$53,""),"+",""),"-","")," ",""),"(",""),")",""),".","")&"?text="&SUBSTITUTE("Hello "&_xlfn.XLOOKUP($A32,'Item Master'!$A$4:$A$53,'Item Master'!$H$4:$H$53,"Supplier")&", we urgently need more "&$B32&". Current stock is only "&TEXT($E32,"0")&" units. Please confirm availability and your fastest lead time. Thank you - Momentum Mind Store."," ","%20"),"💬 ORDER NOW"),"")) | H32: =IF($A32="","",IF($F32="⚠️ REORDER NOW",HYPERLINK("mailto:"&_xlfn.XLOOKUP($A32,'Item Master'!$A$4:$A$53,'Item Master'!$J$4:$J$53,"")&"?subject="&SUBSTITUTE("URGENT restock request - "&$B32&" ("&$A32&")"," ","%20")&"&body="&SUBSTITUTE(SUBSTITUTE("Hello "&_xlfn.XLOOKUP($A32,'Item Master'!$A$4:$A$53,'Item Master'!$H$4:$H$53,"Supplier")&"," & CHAR(10) & "We urgently need to restock "&$B32&" (SKU "&$A32&"). Our current stock is "&TEXT($E32,"0")&" units, which is below our reorder threshold." & CHAR(10) & "Please confirm availability, unit price and lead time by return." & CHAR(10) & "Kind regards," & CHAR(10) & "Momentum Mind Store"," ","%20"),CHAR(10),"%0D%0A"),"✉️ EMAIL"),"")) | I32: =IF($A32="","",$E32*_xlfn.XLOOKUP($A32,'Item Master'!$A$4:$A$53,'Item Master'!$D$4:$D$53,0))
A33: =IF(INDEX('Item Master'!$A$4:$A$53,25)="","",INDEX('Item Master'!$A$4:$A$53,25)) | B33: =IF($A33="","",_xlfn.XLOOKUP($A33,'Item Master'!$A$4:$A$53,'Item Master'!$B$4:$B$53,"")) | C33: =IF($A33="","",SUMIFS('Log Transaction'!$E$4:$E$303,'Log Transaction'!$C$4:$C$303,$A33,'Log Transaction'!$D$4:$D$303,"IN")) | D33: =IF($A33="","",SUMIFS('Log Transaction'!$E$4:$E$303,'Log Transaction'!$C$4:$C$303,$A33,'Log Transaction'!$D$4:$D$303,"OUT")+SUMIFS('Log Transaction'!$E$4:$E$303,'Log Transaction'!$C$4:$C$303,$A33,'Log Transaction'!$D$4:$D$303,"SHRINKAGE")) | E33: =IF($A33="","",$C33-$D33) | F33: =IF($A33="","",IF($E33<=_xlfn.XLOOKUP($A33,'Item Master'!$A$4:$A$53,'Item Master'!$F$4:$F$53,0)*0.1,"⚠️ REORDER NOW","✅ IN STOCK")) | G33: =IF($A33="","",IF($F33="⚠️ REORDER NOW",HYPERLINK("https://wa.me/"&SUBSTITUTE(SUBSTITUTE(SUBSTITUTE(SUBSTITUTE(SUBSTITUTE(SUBSTITUTE(_xlfn.XLOOKUP($A33,'Item Master'!$A$4:$A$53,'Item Master'!$I$4:$I$53,""),"+",""),"-","")," ",""),"(",""),")",""),".","")&"?text="&SUBSTITUTE("Hello "&_xlfn.XLOOKUP($A33,'Item Master'!$A$4:$A$53,'Item Master'!$H$4:$H$53,"Supplier")&", we urgently need more "&$B33&". Current stock is only "&TEXT($E33,"0")&" units. Please confirm availability and your fastest lead time. Thank you - Momentum Mind Store."," ","%20"),"💬 ORDER NOW"),"")) | H33: =IF($A33="","",IF($F33="⚠️ REORDER NOW",HYPERLINK("mailto:"&_xlfn.XLOOKUP($A33,'Item Master'!$A$4:$A$53,'Item Master'!$J$4:$J$53,"")&"?subject="&SUBSTITUTE("URGENT restock request - "&$B33&" ("&$A33&")"," ","%20")&"&body="&SUBSTITUTE(SUBSTITUTE("Hello "&_xlfn.XLOOKUP($A33,'Item Master'!$A$4:$A$53,'Item Master'!$H$4:$H$53,"Supplier")&"," & CHAR(10) & "We urgently need to restock "&$B33&" (SKU "&$A33&"). Our current stock is "&TEXT($E33,"0")&" units, which is below our reorder threshold." & CHAR(10) & "Please confirm availability, unit price and lead time by return." & CHAR(10) & "Kind regards," & CHAR(10) & "Momentum Mind Store"," ","%20"),CHAR(10),"%0D%0A"),"✉️ EMAIL"),"")) | I33: =IF($A33="","",$E33*_xlfn.XLOOKUP($A33,'Item Master'!$A$4:$A$53,'Item Master'!$D$4:$D$53,0))
A34: =IF(INDEX('Item Master'!$A$4:$A$53,26)="","",INDEX('Item Master'!$A$4:$A$53,26)) | B34: =IF($A34="","",_xlfn.XLOOKUP($A34,'Item Master'!$A$4:$A$53,'Item Master'!$B$4:$B$53,"")) | C34: =IF($A34="","",SUMIFS('Log Transaction'!$E$4:$E$303,'Log Transaction'!$C$4:$C$303,$A34,'Log Transaction'!$D$4:$D$303,"IN")) | D34: =IF($A34="","",SUMIFS('Log Transaction'!$E$4:$E$303,'Log Transaction'!$C$4:$C$303,$A34,'Log Transaction'!$D$4:$D$303,"OUT")+SUMIFS('Log Transaction'!$E$4:$E$303,'Log Transaction'!$C$4:$C$303,$A34,'Log Transaction'!$D$4:$D$303,"SHRINKAGE")) | E34: =IF($A34="","",$C34-$D34) | F34: =IF($A34="","",IF($E34<=_xlfn.XLOOKUP($A34,'Item Master'!$A$4:$A$53,'Item Master'!$F$4:$F$53,0)*0.1,"⚠️ REORDER NOW","✅ IN STOCK")) | G34: =IF($A34="","",IF($F34="⚠️ REORDER NOW",HYPERLINK("https://wa.me/"&SUBSTITUTE(SUBSTITUTE(SUBSTITUTE(SUBSTITUTE(SUBSTITUTE(SUBSTITUTE(_xlfn.XLOOKUP($A34,'Item Master'!$A$4:$A$53,'Item Master'!$I$4:$I$53,""),"+",""),"-","")," ",""),"(",""),")",""),".","")&"?text="&SUBSTITUTE("Hello "&_xlfn.XLOOKUP($A34,'Item Master'!$A$4:$A$53,'Item Master'!$H$4:$H$53,"Supplier")&", we urgently need more "&$B34&". Current stock is only "&TEXT($E34,"0")&" units. Please confirm availability and your fastest lead time. Thank you - Momentum Mind Store."," ","%20"),"💬 ORDER NOW"),"")) | H34: =IF($A34="","",IF($F34="⚠️ REORDER NOW",HYPERLINK("mailto:"&_xlfn.XLOOKUP($A34,'Item Master'!$A$4:$A$53,'Item Master'!$J$4:$J$53,"")&"?subject="&SUBSTITUTE("URGENT restock request - "&$B34&" ("&$A34&")"," ","%20")&"&body="&SUBSTITUTE(SUBSTITUTE("Hello "&_xlfn.XLOOKUP($A34,'Item Master'!$A$4:$A$53,'Item Master'!$H$4:$H$53,"Supplier")&"," & CHAR(10) & "We urgently need to restock "&$B34&" (SKU "&$A34&"). Our current stock is "&TEXT($E34,"0")&" units, which is below our reorder threshold." & CHAR(10) & "Please confirm availability, unit price and lead time by return." & CHAR(10) & "Kind regards," & CHAR(10) & "Momentum Mind Store"," ","%20"),CHAR(10),"%0D%0A"),"✉️ EMAIL"),"")) | I34: =IF($A34="","",$E34*_xlfn.XLOOKUP($A34,'Item Master'!$A$4:$A$53,'Item Master'!$D$4:$D$53,0))
A35: =IF(INDEX('Item Master'!$A$4:$A$53,27)="","",INDEX('Item Master'!$A$4:$A$53,27)) | B35: =IF($A35="","",_xlfn.XLOOKUP($A35,'Item Master'!$A$4:$A$53,'Item Master'!$B$4:$B$53,"")) | C35: =IF($A35="","",SUMIFS('Log Transaction'!$E$4:$E$303,'Log Transaction'!$C$4:$C$303,$A35,'Log Transaction'!$D$4:$D$303,"IN")) | D35: =IF($A35="","",SUMIFS('Log Transaction'!$E$4:$E$303,'Log Transaction'!$C$4:$C$303,$A35,'Log Transaction'!$D$4:$D$303,"OUT")+SUMIFS('Log Transaction'!$E$4:$E$303,'Log Transaction'!$C$4:$C$303,$A35,'Log Transaction'!$D$4:$D$303,"SHRINKAGE")) | E35: =IF($A35="","",$C35-$D35) | F35: =IF($A35="","",IF($E35<=_xlfn.XLOOKUP($A35,'Item Master'!$A$4:$A$53,'Item Master'!$F$4:$F$53,0)*0.1,"⚠️ REORDER NOW","✅ IN STOCK")) | G35: =IF($A35="","",IF($F35="⚠️ REORDER NOW",HYPERLINK("https://wa.me/"&SUBSTITUTE(SUBSTITUTE(SUBSTITUTE(SUBSTITUTE(SUBSTITUTE(SUBSTITUTE(_xlfn.XLOOKUP($A35,'Item Master'!$A$4:$A$53,'Item Master'!$I$4:$I$53,""),"+",""),"-","")," ",""),"(",""),")",""),".","")&"?text="&SUBSTITUTE("Hello "&_xlfn.XLOOKUP($A35,'Item Master'!$A$4:$A$53,'Item Master'!$H$4:$H$53,"Supplier")&", we urgently need more "&$B35&". Current stock is only "&TEXT($E35,"0")&" units. Please confirm availability and your fastest lead time. Thank you - Momentum Mind Store."," ","%20"),"💬 ORDER NOW"),"")) | H35: =IF($A35="","",IF($F35="⚠️ REORDER NOW",HYPERLINK("mailto:"&_xlfn.XLOOKUP($A35,'Item Master'!$A$4:$A$53,'Item Master'!$J$4:$J$53,"")&"?subject="&SUBSTITUTE("URGENT restock request - "&$B35&" ("&$A35&")"," ","%20")&"&body="&SUBSTITUTE(SUBSTITUTE("Hello "&_xlfn.XLOOKUP($A35,'Item Master'!$A$4:$A$53,'Item Master'!$H$4:$H$53,"Supplier")&"," & CHAR(10) & "We urgently need to restock "&$B35&" (SKU "&$A35&"). Our current stock is "&TEXT($E35,"0")&" units, which is below our reorder threshold." & CHAR(10) & "Please confirm availability, unit price and lead time by return." & CHAR(10) & "Kind regards," & CHAR(10) & "Momentum Mind Store"," ","%20"),CHAR(10),"%0D%0A"),"✉️ EMAIL"),"")) | I35: =IF($A35="","",$E35*_xlfn.XLOOKUP($A35,'Item Master'!$A$4:$A$53,'Item Master'!$D$4:$D$53,0))
A36: =IF(INDEX('Item Master'!$A$4:$A$53,28)="","",INDEX('Item Master'!$A$4:$A$53,28)) | B36: =IF($A36="","",_xlfn.XLOOKUP($A36,'Item Master'!$A$4:$A$53,'Item Master'!$B$4:$B$53,"")) | C36: =IF($A36="","",SUMIFS('Log Transaction'!$E$4:$E$303,'Log Transaction'!$C$4:$C$303,$A36,'Log Transaction'!$D$4:$D$303,"IN")) | D36: =IF($A36="","",SUMIFS('Log Transaction'!$E$4:$E$303,'Log Transaction'!$C$4:$C$303,$A36,'Log Transaction'!$D$4:$D$303,"OUT")+SUMIFS('Log Transaction'!$E$4:$E$303,'Log Transaction'!$C$4:$C$303,$A36,'Log Transaction'!$D$4:$D$303,"SHRINKAGE")) | E36: =IF($A36="","",$C36-$D36) | F36: =IF($A36="","",IF($E36<=_xlfn.XLOOKUP($A36,'Item Master'!$A$4:$A$53,'Item Master'!$F$4:$F$53,0)*0.1,"⚠️ REORDER NOW","✅ IN STOCK")) | G36: =IF($A36="","",IF($F36="⚠️ REORDER NOW",HYPERLINK("https://wa.me/"&SUBSTITUTE(SUBSTITUTE(SUBSTITUTE(SUBSTITUTE(SUBSTITUTE(SUBSTITUTE(_xlfn.XLOOKUP($A36,'Item Master'!$A$4:$A$53,'Item Master'!$I$4:$I$53,""),"+",""),"-","")," ",""),"(",""),")",""),".","")&"?text="&SUBSTITUTE("Hello "&_xlfn.XLOOKUP($A36,'Item Master'!$A$4:$A$53,'Item Master'!$H$4:$H$53,"Supplier")&", we urgently need more "&$B36&". Current stock is only "&TEXT($E36,"0")&" units. Please confirm availability and your fastest lead time. Thank you - Momentum Mind Store."," ","%20"),"💬 ORDER NOW"),"")) | H36: =IF($A36="","",IF($F36="⚠️ REORDER NOW",HYPERLINK("mailto:"&_xlfn.XLOOKUP($A36,'Item Master'!$A$4:$A$53,'Item Master'!$J$4:$J$53,"")&"?subject="&SUBSTITUTE("URGENT restock request - "&$B36&" ("&$A36&")"," ","%20")&"&body="&SUBSTITUTE(SUBSTITUTE("Hello "&_xlfn.XLOOKUP($A36,'Item Master'!$A$4:$A$53,'Item Master'!$H$4:$H$53,"Supplier")&"," & CHAR(10) & "We urgently need to restock "&$B36&" (SKU "&$A36&"). Our current stock is "&TEXT($E36,"0")&" units, which is below our reorder threshold." & CHAR(10) & "Please confirm availability, unit price and lead time by return." & CHAR(10) & "Kind regards," & CHAR(10) & "Momentum Mind Store"," ","%20"),CHAR(10),"%0D%0A"),"✉️ EMAIL"),"")) | I36: =IF($A36="","",$E36*_xlfn.XLOOKUP($A36,'Item Master'!$A$4:$A$53,'Item Master'!$D$4:$D$53,0))
A37: =IF(INDEX('Item Master'!$A$4:$A$53,29)="","",INDEX('Item Master'!$A$4:$A$53,29)) | B37: =IF($A37="","",_xlfn.XLOOKUP($A37,'Item Master'!$A$4:$A$53,'Item Master'!$B$4:$B$53,"")) | C37: =IF($A37="","",SUMIFS('Log Transaction'!$E$4:$E$303,'Log Transaction'!$C$4:$C$303,$A37,'Log Transaction'!$D$4:$D$303,"IN")) | D37: =IF($A37="","",SUMIFS('Log Transaction'!$E$4:$E$303,'Log Transaction'!$C$4:$C$303,$A37,'Log Transaction'!$D$4:$D$303,"OUT")+SUMIFS('Log Transaction'!$E$4:$E$303,'Log Transaction'!$C$4:$C$303,$A37,'Log Transaction'!$D$4:$D$303,"SHRINKAGE")) | E37: =IF($A37="","",$C37-$D37) | F37: =IF($A37="","",IF($E37<=_xlfn.XLOOKUP($A37,'Item Master'!$A$4:$A$53,'Item Master'!$F$4:$F$53,0)*0.1,"⚠️ REORDER NOW","✅ IN STOCK")) | G37: =IF($A37="","",IF($F37="⚠️ REORDER NOW",HYPERLINK("https://wa.me/"&SUBSTITUTE(SUBSTITUTE(SUBSTITUTE(SUBSTITUTE(SUBSTITUTE(SUBSTITUTE(_xlfn.XLOOKUP($A37,'Item Master'!$A$4:$A$53,'Item Master'!$I$4:$I$53,""),"+",""),"-","")," ",""),"(",""),")",""),".","")&"?text="&SUBSTITUTE("Hello "&_xlfn.XLOOKUP($A37,'Item Master'!$A$4:$A$53,'Item Master'!$H$4:$H$53,"Supplier")&", we urgently need more "&$B37&". Current stock is only "&TEXT($E37,"0")&" units. Please confirm availability and your fastest lead time. Thank you - Momentum Mind Store."," ","%20"),"💬 ORDER NOW"),"")) | H37: =IF($A37="","",IF($F37="⚠️ REORDER NOW",HYPERLINK("mailto:"&_xlfn.XLOOKUP($A37,'Item Master'!$A$4:$A$53,'Item Master'!$J$4:$J$53,"")&"?subject="&SUBSTITUTE("URGENT restock request - "&$B37&" ("&$A37&")"," ","%20")&"&body="&SUBSTITUTE(SUBSTITUTE("Hello "&_xlfn.XLOOKUP($A37,'Item Master'!$A$4:$A$53,'Item Master'!$H$4:$H$53,"Supplier")&"," & CHAR(10) & "We urgently need to restock "&$B37&" (SKU "&$A37&"). Our current stock is "&TEXT($E37,"0")&" units, which is below our reorder threshold." & CHAR(10) & "Please confirm availability, unit price and lead time by return." & CHAR(10) & "Kind regards," & CHAR(10) & "Momentum Mind Store"," ","%20"),CHAR(10),"%0D%0A"),"✉️ EMAIL"),"")) | I37: =IF($A37="","",$E37*_xlfn.XLOOKUP($A37,'Item Master'!$A$4:$A$53,'Item Master'!$D$4:$D$53,0))
A38: =IF(INDEX('Item Master'!$A$4:$A$53,30)="","",INDEX('Item Master'!$A$4:$A$53,30)) | B38: =IF($A38="","",_xlfn.XLOOKUP($A38,'Item Master'!$A$4:$A$53,'Item Master'!$B$4:$B$53,"")) | C38: =IF($A38="","",SUMIFS('Log Transaction'!$E$4:$E$303,'Log Transaction'!$C$4:$C$303,$A38,'Log Transaction'!$D$4:$D$303,"IN")) | D38: =IF($A38="","",SUMIFS('Log Transaction'!$E$4:$E$303,'Log Transaction'!$C$4:$C$303,$A38,'Log Transaction'!$D$4:$D$303,"OUT")+SUMIFS('Log Transaction'!$E$4:$E$303,'Log Transaction'!$C$4:$C$303,$A38,'Log Transaction'!$D$4:$D$303,"SHRINKAGE")) | E38: =IF($A38="","",$C38-$D38) | F38: =IF($A38="","",IF($E38<=_xlfn.XLOOKUP($A38,'Item Master'!$A$4:$A$53,'Item Master'!$F$4:$F$53,0)*0.1,"⚠️ REORDER NOW","✅ IN STOCK")) | G38: =IF($A38="","",IF($F38="⚠️ REORDER NOW",HYPERLINK("https://wa.me/"&SUBSTITUTE(SUBSTITUTE(SUBSTITUTE(SUBSTITUTE(SUBSTITUTE(SUBSTITUTE(_xlfn.XLOOKUP($A38,'Item Master'!$A$4:$A$53,'Item Master'!$I$4:$I$53,""),"+",""),"-","")," ",""),"(",""),")",""),".","")&"?text="&SUBSTITUTE("Hello "&_xlfn.XLOOKUP($A38,'Item Master'!$A$4:$A$53,'Item Master'!$H$4:$H$53,"Supplier")&", we urgently need more "&$B38&". Current stock is only "&TEXT($E38,"0")&" units. Please confirm availability and your fastest lead time. Thank you - Momentum Mind Store."," ","%20"),"💬 ORDER NOW"),"")) | H38: =IF($A38="","",IF($F38="⚠️ REORDER NOW",HYPERLINK("mailto:"&_xlfn.XLOOKUP($A38,'Item Master'!$A$4:$A$53,'Item Master'!$J$4:$J$53,"")&"?subject="&SUBSTITUTE("URGENT restock request - "&$B38&" ("&$A38&")"," ","%20")&"&body="&SUBSTITUTE(SUBSTITUTE("Hello "&_xlfn.XLOOKUP($A38,'Item Master'!$A$4:$A$53,'Item Master'!$H$4:$H$53,"Supplier")&"," & CHAR(10) & "We urgently need to restock "&$B38&" (SKU "&$A38&"). Our current stock is "&TEXT($E38,"0")&" units, which is below our reorder threshold." & CHAR(10) & "Please confirm availability, unit price and lead time by return." & CHAR(10) & "Kind regards," & CHAR(10) & "Momentum Mind Store"," ","%20"),CHAR(10),"%0D%0A"),"✉️ EMAIL"),"")) | I38: =IF($A38="","",$E38*_xlfn.XLOOKUP($A38,'Item Master'!$A$4:$A$53,'Item Master'!$D$4:$D$53,0))
A39: =IF(INDEX('Item Master'!$A$4:$A$53,31)="","",INDEX('Item Master'!$A$4:$A$53,31)) | B39: =IF($A39="","",_xlfn.XLOOKUP($A39,'Item Master'!$A$4:$A$53,'Item Master'!$B$4:$B$53,"")) | C39: =IF($A39="","",SUMIFS('Log Transaction'!$E$4:$E$303,'Log Transaction'!$C$4:$C$303,$A39,'Log Transaction'!$D$4:$D$303,"IN")) | D39: =IF($A39="","",SUMIFS('Log Transaction'!$E$4:$E$303,'Log Transaction'!$C$4:$C$303,$A39,'Log Transaction'!$D$4:$D$303,"OUT")+SUMIFS('Log Transaction'!$E$4:$E$303,'Log Transaction'!$C$4:$C$303,$A39,'Log Transaction'!$D$4:$D$303,"SHRINKAGE")) | E39: =IF($A39="","",$C39-$D39) | F39: =IF($A39="","",IF($E39<=_xlfn.XLOOKUP($A39,'Item Master'!$A$4:$A$53,'Item Master'!$F$4:$F$53,0)*0.1,"⚠️ REORDER NOW","✅ IN STOCK")) | G39: =IF($A39="","",IF($F39="⚠️ REORDER NOW",HYPERLINK("https://wa.me/"&SUBSTITUTE(SUBSTITUTE(SUBSTITUTE(SUBSTITUTE(SUBSTITUTE(SUBSTITUTE(_xlfn.XLOOKUP($A39,'Item Master'!$A$4:$A$53,'Item Master'!$I$4:$I$53,""),"+",""),"-","")," ",""),"(",""),")",""),".","")&"?text="&SUBSTITUTE("Hello "&_xlfn.XLOOKUP($A39,'Item Master'!$A$4:$A$53,'Item Master'!$H$4:$H$53,"Supplier")&", we urgently need more "&$B39&". Current stock is only "&TEXT($E39,"0")&" units. Please confirm availability and your fastest lead time. Thank you - Momentum Mind Store."," ","%20"),"💬 ORDER NOW"),"")) | H39: =IF($A39="","",IF($F39="⚠️ REORDER NOW",HYPERLINK("mailto:"&_xlfn.XLOOKUP($A39,'Item Master'!$A$4:$A$53,'Item Master'!$J$4:$J$53,"")&"?subject="&SUBSTITUTE("URGENT restock request - "&$B39&" ("&$A39&")"," ","%20")&"&body="&SUBSTITUTE(SUBSTITUTE("Hello "&_xlfn.XLOOKUP($A39,'Item Master'!$A$4:$A$53,'Item Master'!$H$4:$H$53,"Supplier")&"," & CHAR(10) & "We urgently need to restock "&$B39&" (SKU "&$A39&"). Our current stock is "&TEXT($E39,"0")&" units, which is below our reorder threshold." & CHAR(10) & "Please confirm availability, unit price and lead time by return." & CHAR(10) & "Kind regards," & CHAR(10) & "Momentum Mind Store"," ","%20"),CHAR(10),"%0D%0A"),"✉️ EMAIL"),"")) | I39: =IF($A39="","",$E39*_xlfn.XLOOKUP($A39,'Item Master'!$A$4:$A$53,'Item Master'!$D$4:$D$53,0))
A40: =IF(INDEX('Item Master'!$A$4:$A$53,32)="","",INDEX('Item Master'!$A$4:$A$53,32)) | B40: =IF($A40="","",_xlfn.XLOOKUP($A40,'Item Master'!$A$4:$A$53,'Item Master'!$B$4:$B$53,"")) | C40: =IF($A40="","",SUMIFS('Log Transaction'!$E$4:$E$303,'Log Transaction'!$C$4:$C$303,$A40,'Log Transaction'!$D$4:$D$303,"IN")) | D40: =IF($A40="","",SUMIFS('Log Transaction'!$E$4:$E$303,'Log Transaction'!$C$4:$C$303,$A40,'Log Transaction'!$D$4:$D$303,"OUT")+SUMIFS('Log Transaction'!$E$4:$E$303,'Log Transaction'!$C$4:$C$303,$A40,'Log Transaction'!$D$4:$D$303,"SHRINKAGE")) | E40: =IF($A40="","",$C40-$D40) | F40: =IF($A40="","",IF($E40<=_xlfn.XLOOKUP($A40,'Item Master'!$A$4:$A$53,'Item Master'!$F$4:$F$53,0)*0.1,"⚠️ REORDER NOW","✅ IN STOCK")) | G40: =IF($A40="","",IF($F40="⚠️ REORDER NOW",HYPERLINK("https://wa.me/"&SUBSTITUTE(SUBSTITUTE(SUBSTITUTE(SUBSTITUTE(SUBSTITUTE(SUBSTITUTE(_xlfn.XLOOKUP($A40,'Item Master'!$A$4:$A$53,'Item Master'!$I$4:$I$53,""),"+",""),"-","")," ",""),"(",""),")",""),".","")&"?text="&SUBSTITUTE("Hello "&_xlfn.XLOOKUP($A40,'Item Master'!$A$4:$A$53,'Item Master'!$H$4:$H$53,"Supplier")&", we urgently need more "&$B40&". Current stock is only "&TEXT($E40,"0")&" units. Please confirm availability and your fastest lead time. Thank you - Momentum Mind Store."," ","%20"),"💬 ORDER NOW"),"")) | H40: =IF($A40="","",IF($F40="⚠️ REORDER NOW",HYPERLINK("mailto:"&_xlfn.XLOOKUP($A40,'Item Master'!$A$4:$A$53,'Item Master'!$J$4:$J$53,"")&"?subject="&SUBSTITUTE("URGENT restock request - "&$B40&" ("&$A40&")"," ","%20")&"&body="&SUBSTITUTE(SUBSTITUTE("Hello "&_xlfn.XLOOKUP($A40,'Item Master'!$A$4:$A$53,'Item Master'!$H$4:$H$53,"Supplier")&"," & CHAR(10) & "We urgently need to restock "&$B40&" (SKU "&$A40&"). Our current stock is "&TEXT($E40,"0")&" units, which is below our reorder threshold." & CHAR(10) & "Please confirm availability, unit price and lead time by return." & CHAR(10) & "Kind regards," & CHAR(10) & "Momentum Mind Store"," ","%20"),CHAR(10),"%0D%0A"),"✉️ EMAIL"),"")) | I40: =IF($A40="","",$E40*_xlfn.XLOOKUP($A40,'Item Master'!$A$4:$A$53,'Item Master'!$D$4:$D$53,0))
A41: =IF(INDEX('Item Master'!$A$4:$A$53,33)="","",INDEX('Item Master'!$A$4:$A$53,33)) | B41: =IF($A41="","",_xlfn.XLOOKUP($A41,'Item Master'!$A$4:$A$53,'Item Master'!$B$4:$B$53,"")) | C41: =IF($A41="","",SUMIFS('Log Transaction'!$E$4:$E$303,'Log Transaction'!$C$4:$C$303,$A41,'Log Transaction'!$D$4:$D$303,"IN")) | D41: =IF($A41="","",SUMIFS('Log Transaction'!$E$4:$E$303,'Log Transaction'!$C$4:$C$303,$A41,'Log Transaction'!$D$4:$D$303,"OUT")+SUMIFS('Log Transaction'!$E$4:$E$303,'Log Transaction'!$C$4:$C$303,$A41,'Log Transaction'!$D$4:$D$303,"SHRINKAGE")) | E41: =IF($A41="","",$C41-$D41) | F41: =IF($A41="","",IF($E41<=_xlfn.XLOOKUP($A41,'Item Master'!$A$4:$A$53,'Item Master'!$F$4:$F$53,0)*0.1,"⚠️ REORDER NOW","✅ IN STOCK")) | G41: =IF($A41="","",IF($F41="⚠️ REORDER NOW",HYPERLINK("https://wa.me/"&SUBSTITUTE(SUBSTITUTE(SUBSTITUTE(SUBSTITUTE(SUBSTITUTE(SUBSTITUTE(_xlfn.XLOOKUP($A41,'Item Master'!$A$4:$A$53,'Item Master'!$I$4:$I$53,""),"+",""),"-","")," ",""),"(",""),")",""),".","")&"?text="&SUBSTITUTE("Hello "&_xlfn.XLOOKUP($A41,'Item Master'!$A$4:$A$53,'Item Master'!$H$4:$H$53,"Supplier")&", we urgently need more "&$B41&". Current stock is only "&TEXT($E41,"0")&" units. Please confirm availability and your fastest lead time. Thank you - Momentum Mind Store."," ","%20"),"💬 ORDER NOW"),"")) | H41: =IF($A41="","",IF($F41="⚠️ REORDER NOW",HYPERLINK("mailto:"&_xlfn.XLOOKUP($A41,'Item Master'!$A$4:$A$53,'Item Master'!$J$4:$J$53,"")&"?subject="&SUBSTITUTE("URGENT restock request - "&$B41&" ("&$A41&")"," ","%20")&"&body="&SUBSTITUTE(SUBSTITUTE("Hello "&_xlfn.XLOOKUP($A41,'Item Master'!$A$4:$A$53,'Item Master'!$H$4:$H$53,"Supplier")&"," & CHAR(10) & "We urgently need to restock "&$B41&" (SKU "&$A41&"). Our current stock is "&TEXT($E41,"0")&" units, which is below our reorder threshold." & CHAR(10) & "Please confirm availability, unit price and lead time by return." & CHAR(10) & "Kind regards," & CHAR(10) & "Momentum Mind Store"," ","%20"),CHAR(10),"%0D%0A"),"✉️ EMAIL"),"")) | I41: =IF($A41="","",$E41*_xlfn.XLOOKUP($A41,'Item Master'!$A$4:$A$53,'Item Master'!$D$4:$D$53,0))
A42: =IF(INDEX('Item Master'!$A$4:$A$53,34)="","",INDEX('Item Master'!$A$4:$A$53,34)) | B42: =IF($A42="","",_xlfn.XLOOKUP($A42,'Item Master'!$A$4:$A$53,'Item Master'!$B$4:$B$53,"")) | C42: =IF($A42="","",SUMIFS('Log Transaction'!$E$4:$E$303,'Log Transaction'!$C$4:$C$303,$A42,'Log Transaction'!$D$4:$D$303,"IN")) | D42: =IF($A42="","",SUMIFS('Log Transaction'!$E$4:$E$303,'Log Transaction'!$C$4:$C$303,$A42,'Log Transaction'!$D$4:$D$303,"OUT")+SUMIFS('Log Transaction'!$E$4:$E$303,'Log Transaction'!$C$4:$C$303,$A42,'Log Transaction'!$D$4:$D$303,"SHRINKAGE")) | E42: =IF($A42="","",$C42-$D42) | F42: =IF($A42="","",IF($E42<=_xlfn.XLOOKUP($A42,'Item Master'!$A$4:$A$53,'Item Master'!$F$4:$F$53,0)*0.1,"⚠️ REORDER NOW","✅ IN STOCK")) | G42: =IF($A42="","",IF($F42="⚠️ REORDER NOW",HYPERLINK("https://wa.me/"&SUBSTITUTE(SUBSTITUTE(SUBSTITUTE(SUBSTITUTE(SUBSTITUTE(SUBSTITUTE(_xlfn.XLOOKUP($A42,'Item Master'!$A$4:$A$53,'Item Master'!$I$4:$I$53,""),"+",""),"-","")," ",""),"(",""),")",""),".","")&"?text="&SUBSTITUTE("Hello "&_xlfn.XLOOKUP($A42,'Item Master'!$A$4:$A$53,'Item Master'!$H$4:$H$53,"Supplier")&", we urgently need more "&$B42&". Current stock is only "&TEXT($E42,"0")&" units. Please confirm availability and your fastest lead time. Thank you - Momentum Mind Store."," ","%20"),"💬 ORDER NOW"),"")) | H42: =IF($A42="","",IF($F42="⚠️ REORDER NOW",HYPERLINK("mailto:"&_xlfn.XLOOKUP($A42,'Item Master'!$A$4:$A$53,'Item Master'!$J$4:$J$53,"")&"?subject="&SUBSTITUTE("URGENT restock request - "&$B42&" ("&$A42&")"," ","%20")&"&body="&SUBSTITUTE(SUBSTITUTE("Hello "&_xlfn.XLOOKUP($A42,'Item Master'!$A$4:$A$53,'Item Master'!$H$4:$H$53,"Supplier")&"," & CHAR(10) & "We urgently need to restock "&$B42&" (SKU "&$A42&"). Our current stock is "&TEXT($E42,"0")&" units, which is below our reorder threshold." & CHAR(10) & "Please confirm availability, unit price and lead time by return." & CHAR(10) & "Kind regards," & CHAR(10) & "Momentum Mind Store"," ","%20"),CHAR(10),"%0D%0A"),"✉️ EMAIL"),"")) | I42: =IF($A42="","",$E42*_xlfn.XLOOKUP($A42,'Item Master'!$A$4:$A$53,'Item Master'!$D$4:$D$53,0))
A43: =IF(INDEX('Item Master'!$A$4:$A$53,35)="","",INDEX('Item Master'!$A$4:$A$53,35)) | B43: =IF($A43="","",_xlfn.XLOOKUP($A43,'Item Master'!$A$4:$A$53,'Item Master'!$B$4:$B$53,"")) | C43: =IF($A43="","",SUMIFS('Log Transaction'!$E$4:$E$303,'Log Transaction'!$C$4:$C$303,$A43,'Log Transaction'!$D$4:$D$303,"IN")) | D43: =IF($A43="","",SUMIFS('Log Transaction'!$E$4:$E$303,'Log Transaction'!$C$4:$C$303,$A43,'Log Transaction'!$D$4:$D$303,"OUT")+SUMIFS('Log Transaction'!$E$4:$E$303,'Log Transaction'!$C$4:$C$303,$A43,'Log Transaction'!$D$4:$D$303,"SHRINKAGE")) | E43: =IF($A43="","",$C43-$D43) | F43: =IF($A43="","",IF($E43<=_xlfn.XLOOKUP($A43,'Item Master'!$A$4:$A$53,'Item Master'!$F$4:$F$53,0)*0.1,"⚠️ REORDER NOW","✅ IN STOCK")) | G43: =IF($A43="","",IF($F43="⚠️ REORDER NOW",HYPERLINK("https://wa.me/"&SUBSTITUTE(SUBSTITUTE(SUBSTITUTE(SUBSTITUTE(SUBSTITUTE(SUBSTITUTE(_xlfn.XLOOKUP($A43,'Item Master'!$A$4:$A$53,'Item Master'!$I$4:$I$53,""),"+",""),"-","")," ",""),"(",""),")",""),".","")&"?text="&SUBSTITUTE("Hello "&_xlfn.XLOOKUP($A43,'Item Master'!$A$4:$A$53,'Item Master'!$H$4:$H$53,"Supplier")&", we urgently need more "&$B43&". Current stock is only "&TEXT($E43,"0")&" units. Please confirm availability and your fastest lead time. Thank you - Momentum Mind Store."," ","%20"),"💬 ORDER NOW"),"")) | H43: =IF($A43="","",IF($F43="⚠️ REORDER NOW",HYPERLINK("mailto:"&_xlfn.XLOOKUP($A43,'Item Master'!$A$4:$A$53,'Item Master'!$J$4:$J$53,"")&"?subject="&SUBSTITUTE("URGENT restock request - "&$B43&" ("&$A43&")"," ","%20")&"&body="&SUBSTITUTE(SUBSTITUTE("Hello "&_xlfn.XLOOKUP($A43,'Item Master'!$A$4:$A$53,'Item Master'!$H$4:$H$53,"Supplier")&"," & CHAR(10) & "We urgently need to restock "&$B43&" (SKU "&$A43&"). Our current stock is "&TEXT($E43,"0")&" units, which is below our reorder threshold." & CHAR(10) & "Please confirm availability, unit price and lead time by return." & CHAR(10) & "Kind regards," & CHAR(10) & "Momentum Mind Store"," ","%20"),CHAR(10),"%0D%0A"),"✉️ EMAIL"),"")) | I43: =IF($A43="","",$E43*_xlfn.XLOOKUP($A43,'Item Master'!$A$4:$A$53,'Item Master'!$D$4:$D$53,0))
A44: =IF(INDEX('Item Master'!$A$4:$A$53,36)="","",INDEX('Item Master'!$A$4:$A$53,36)) | B44: =IF($A44="","",_xlfn.XLOOKUP($A44,'Item Master'!$A$4:$A$53,'Item Master'!$B$4:$B$53,"")) | C44: =IF($A44="","",SUMIFS('Log Transaction'!$E$4:$E$303,'Log Transaction'!$C$4:$C$303,$A44,'Log Transaction'!$D$4:$D$303,"IN")) | D44: =IF($A44="","",SUMIFS('Log Transaction'!$E$4:$E$303,'Log Transaction'!$C$4:$C$303,$A44,'Log Transaction'!$D$4:$D$303,"OUT")+SUMIFS('Log Transaction'!$E$4:$E$303,'Log Transaction'!$C$4:$C$303,$A44,'Log Transaction'!$D$4:$D$303,"SHRINKAGE")) | E44: =IF($A44="","",$C44-$D44) | F44: =IF($A44="","",IF($E44<=_xlfn.XLOOKUP($A44,'Item Master'!$A$4:$A$53,'Item Master'!$F$4:$F$53,0)*0.1,"⚠️ REORDER NOW","✅ IN STOCK")) | G44: =IF($A44="","",IF($F44="⚠️ REORDER NOW",HYPERLINK("https://wa.me/"&SUBSTITUTE(SUBSTITUTE(SUBSTITUTE(SUBSTITUTE(SUBSTITUTE(SUBSTITUTE(_xlfn.XLOOKUP($A44,'Item Master'!$A$4:$A$53,'Item Master'!$I$4:$I$53,""),"+",""),"-","")," ",""),"(",""),")",""),".","")&"?text="&SUBSTITUTE("Hello "&_xlfn.XLOOKUP($A44,'Item Master'!$A$4:$A$53,'Item Master'!$H$4:$H$53,"Supplier")&", we urgently need more "&$B44&". Current stock is only "&TEXT($E44,"0")&" units. Please confirm availability and your fastest lead time. Thank you - Momentum Mind Store."," ","%20"),"💬 ORDER NOW"),"")) | H44: =IF($A44="","",IF($F44="⚠️ REORDER NOW",HYPERLINK("mailto:"&_xlfn.XLOOKUP($A44,'Item Master'!$A$4:$A$53,'Item Master'!$J$4:$J$53,"")&"?subject="&SUBSTITUTE("URGENT restock request - "&$B44&" ("&$A44&")"," ","%20")&"&body="&SUBSTITUTE(SUBSTITUTE("Hello "&_xlfn.XLOOKUP($A44,'Item Master'!$A$4:$A$53,'Item Master'!$H$4:$H$53,"Supplier")&"," & CHAR(10) & "We urgently need to restock "&$B44&" (SKU "&$A44&"). Our current stock is "&TEXT($E44,"0")&" units, which is below our reorder threshold." & CHAR(10) & "Please confirm availability, unit price and lead time by return." & CHAR(10) & "Kind regards," & CHAR(10) & "Momentum Mind Store"," ","%20"),CHAR(10),"%0D%0A"),"✉️ EMAIL"),"")) | I44: =IF($A44="","",$E44*_xlfn.XLOOKUP($A44,'Item Master'!$A$4:$A$53,'Item Master'!$D$4:$D$53,0))
A45: =IF(INDEX('Item Master'!$A$4:$A$53,37)="","",INDEX('Item Master'!$A$4:$A$53,37)) | B45: =IF($A45="","",_xlfn.XLOOKUP($A45,'Item Master'!$A$4:$A$53,'Item Master'!$B$4:$B$53,"")) | C45: =IF($A45="","",SUMIFS('Log Transaction'!$E$4:$E$303,'Log Transaction'!$C$4:$C$303,$A45,'Log Transaction'!$D$4:$D$303,"IN")) | D45: =IF($A45="","",SUMIFS('Log Transaction'!$E$4:$E$303,'Log Transaction'!$C$4:$C$303,$A45,'Log Transaction'!$D$4:$D$303,"OUT")+SUMIFS('Log Transaction'!$E$4:$E$303,'Log Transaction'!$C$4:$C$303,$A45,'Log Transaction'!$D$4:$D$303,"SHRINKAGE")) | E45: =IF($A45="","",$C45-$D45) | F45: =IF($A45="","",IF($E45<=_xlfn.XLOOKUP($A45,'Item Master'!$A$4:$A$53,'Item Master'!$F$4:$F$53,0)*0.1,"⚠️ REORDER NOW","✅ IN STOCK")) | G45: =IF($A45="","",IF($F45="⚠️ REORDER NOW",HYPERLINK("https://wa.me/"&SUBSTITUTE(SUBSTITUTE(SUBSTITUTE(SUBSTITUTE(SUBSTITUTE(SUBSTITUTE(_xlfn.XLOOKUP($A45,'Item Master'!$A$4:$A$53,'Item Master'!$I$4:$I$53,""),"+",""),"-","")," ",""),"(",""),")",""),".","")&"?text="&SUBSTITUTE("Hello "&_xlfn.XLOOKUP($A45,'Item Master'!$A$4:$A$53,'Item Master'!$H$4:$H$53,"Supplier")&", we urgently need more "&$B45&". Current stock is only "&TEXT($E45,"0")&" units. Please confirm availability and your fastest lead time. Thank you - Momentum Mind Store."," ","%20"),"💬 ORDER NOW"),"")) | H45: =IF($A45="","",IF($F45="⚠️ REORDER NOW",HYPERLINK("mailto:"&_xlfn.XLOOKUP($A45,'Item Master'!$A$4:$A$53,'Item Master'!$J$4:$J$53,"")&"?subject="&SUBSTITUTE("URGENT restock request - "&$B45&" ("&$A45&")"," ","%20")&"&body="&SUBSTITUTE(SUBSTITUTE("Hello "&_xlfn.XLOOKUP($A45,'Item Master'!$A$4:$A$53,'Item Master'!$H$4:$H$53,"Supplier")&"," & CHAR(10) & "We urgently need to restock "&$B45&" (SKU "&$A45&"). Our current stock is "&TEXT($E45,"0")&" units, which is below our reorder threshold." & CHAR(10) & "Please confirm availability, unit price and lead time by return." & CHAR(10) & "Kind regards," & CHAR(10) & "Momentum Mind Store"," ","%20"),CHAR(10),"%0D%0A"),"✉️ EMAIL"),"")) | I45: =IF($A45="","",$E45*_xlfn.XLOOKUP($A45,'Item Master'!$A$4:$A$53,'Item Master'!$D$4:$D$53,0))
A46: =IF(INDEX('Item Master'!$A$4:$A$53,38)="","",INDEX('Item Master'!$A$4:$A$53,38)) | B46: =IF($A46="","",_xlfn.XLOOKUP($A46,'Item Master'!$A$4:$A$53,'Item Master'!$B$4:$B$53,"")) | C46: =IF($A46="","",SUMIFS('Log Transaction'!$E$4:$E$303,'Log Transaction'!$C$4:$C$303,$A46,'Log Transaction'!$D$4:$D$303,"IN")) | D46: =IF($A46="","",SUMIFS('Log Transaction'!$E$4:$E$303,'Log Transaction'!$C$4:$C$303,$A46,'Log Transaction'!$D$4:$D$303,"OUT")+SUMIFS('Log Transaction'!$E$4:$E$303,'Log Transaction'!$C$4:$C$303,$A46,'Log Transaction'!$D$4:$D$303,"SHRINKAGE")) | E46: =IF($A46="","",$C46-$D46) | F46: =IF($A46="","",IF($E46<=_xlfn.XLOOKUP($A46,'Item Master'!$A$4:$A$53,'Item Master'!$F$4:$F$53,0)*0.1,"⚠️ REORDER NOW","✅ IN STOCK")) | G46: =IF($A46="","",IF($F46="⚠️ REORDER NOW",HYPERLINK("https://wa.me/"&SUBSTITUTE(SUBSTITUTE(SUBSTITUTE(SUBSTITUTE(SUBSTITUTE(SUBSTITUTE(_xlfn.XLOOKUP($A46,'Item Master'!$A$4:$A$53,'Item Master'!$I$4:$I$53,""),"+",""),"-","")," ",""),"(",""),")",""),".","")&"?text="&SUBSTITUTE("Hello "&_xlfn.XLOOKUP($A46,'Item Master'!$A$4:$A$53,'Item Master'!$H$4:$H$53,"Supplier")&", we urgently need more "&$B46&". Current stock is only "&TEXT($E46,"0")&" units. Please confirm availability and your fastest lead time. Thank you - Momentum Mind Store."," ","%20"),"💬 ORDER NOW"),"")) | H46: =IF($A46="","",IF($F46="⚠️ REORDER NOW",HYPERLINK("mailto:"&_xlfn.XLOOKUP($A46,'Item Master'!$A$4:$A$53,'Item Master'!$J$4:$J$53,"")&"?subject="&SUBSTITUTE("URGENT restock request - "&$B46&" ("&$A46&")"," ","%20")&"&body="&SUBSTITUTE(SUBSTITUTE("Hello "&_xlfn.XLOOKUP($A46,'Item Master'!$A$4:$A$53,'Item Master'!$H$4:$H$53,"Supplier")&"," & CHAR(10) & "We urgently need to restock "&$B46&" (SKU "&$A46&"). Our current stock is "&TEXT($E46,"0")&" units, which is below our reorder threshold." & CHAR(10) & "Please confirm availability, unit price and lead time by return." & CHAR(10) & "Kind regards," & CHAR(10) & "Momentum Mind Store"," ","%20"),CHAR(10),"%0D%0A"),"✉️ EMAIL"),"")) | I46: =IF($A46="","",$E46*_xlfn.XLOOKUP($A46,'Item Master'!$A$4:$A$53,'Item Master'!$D$4:$D$53,0))
A47: =IF(INDEX('Item Master'!$A$4:$A$53,39)="","",INDEX('Item Master'!$A$4:$A$53,39)) | B47: =IF($A47="","",_xlfn.XLOOKUP($A47,'Item Master'!$A$4:$A$53,'Item Master'!$B$4:$B$53,"")) | C47: =IF($A47="","",SUMIFS('Log Transaction'!$E$4:$E$303,'Log Transaction'!$C$4:$C$303,$A47,'Log Transaction'!$D$4:$D$303,"IN")) | D47: =IF($A47="","",SUMIFS('Log Transaction'!$E$4:$E$303,'Log Transaction'!$C$4:$C$303,$A47,'Log Transaction'!$D$4:$D$303,"OUT")+SUMIFS('Log Transaction'!$E$4:$E$303,'Log Transaction'!$C$4:$C$303,$A47,'Log Transaction'!$D$4:$D$303,"SHRINKAGE")) | E47: =IF($A47="","",$C47-$D47) | F47: =IF($A47="","",IF($E47<=_xlfn.XLOOKUP($A47,'Item Master'!$A$4:$A$53,'Item Master'!$F$4:$F$53,0)*0.1,"⚠️ REORDER NOW","✅ IN STOCK")) | G47: =IF($A47="","",IF($F47="⚠️ REORDER NOW",HYPERLINK("https://wa.me/"&SUBSTITUTE(SUBSTITUTE(SUBSTITUTE(SUBSTITUTE(SUBSTITUTE(SUBSTITUTE(_xlfn.XLOOKUP($A47,'Item Master'!$A$4:$A$53,'Item Master'!$I$4:$I$53,""),"+",""),"-","")," ",""),"(",""),")",""),".","")&"?text="&SUBSTITUTE("Hello "&_xlfn.XLOOKUP($A47,'Item Master'!$A$4:$A$53,'Item Master'!$H$4:$H$53,"Supplier")&", we urgently need more "&$B47&". Current stock is only "&TEXT($E47,"0")&" units. Please confirm availability and your fastest lead time. Thank you - Momentum Mind Store."," ","%20"),"💬 ORDER NOW"),"")) | H47: =IF($A47="","",IF($F47="⚠️ REORDER NOW",HYPERLINK("mailto:"&_xlfn.XLOOKUP($A47,'Item Master'!$A$4:$A$53,'Item Master'!$J$4:$J$53,"")&"?subject="&SUBSTITUTE("URGENT restock request - "&$B47&" ("&$A47&")"," ","%20")&"&body="&SUBSTITUTE(SUBSTITUTE("Hello "&_xlfn.XLOOKUP($A47,'Item Master'!$A$4:$A$53,'Item Master'!$H$4:$H$53,"Supplier")&"," & CHAR(10) & "We urgently need to restock "&$B47&" (SKU "&$A47&"). Our current stock is "&TEXT($E47,"0")&" units, which is below our reorder threshold." & CHAR(10) & "Please confirm availability, unit price and lead time by return." & CHAR(10) & "Kind regards," & CHAR(10) & "Momentum Mind Store"," ","%20"),CHAR(10),"%0D%0A"),"✉️ EMAIL"),"")) | I47: =IF($A47="","",$E47*_xlfn.XLOOKUP($A47,'Item Master'!$A$4:$A$53,'Item Master'!$D$4:$D$53,0))
A48: =IF(INDEX('Item Master'!$A$4:$A$53,40)="","",INDEX('Item Master'!$A$4:$A$53,40)) | B48: =IF($A48="","",_xlfn.XLOOKUP($A48,'Item Master'!$A$4:$A$53,'Item Master'!$B$4:$B$53,"")) | C48: =IF($A48="","",SUMIFS('Log Transaction'!$E$4:$E$303,'Log Transaction'!$C$4:$C$303,$A48,'Log Transaction'!$D$4:$D$303,"IN")) | D48: =IF($A48="","",SUMIFS('Log Transaction'!$E$4:$E$303,'Log Transaction'!$C$4:$C$303,$A48,'Log Transaction'!$D$4:$D$303,"OUT")+SUMIFS('Log Transaction'!$E$4:$E$303,'Log Transaction'!$C$4:$C$303,$A48,'Log Transaction'!$D$4:$D$303,"SHRINKAGE")) | E48: =IF($A48="","",$C48-$D48) | F48: =IF($A48="","",IF($E48<=_xlfn.XLOOKUP($A48,'Item Master'!$A$4:$A$53,'Item Master'!$F$4:$F$53,0)*0.1,"⚠️ REORDER NOW","✅ IN STOCK")) | G48: =IF($A48="","",IF($F48="⚠️ REORDER NOW",HYPERLINK("https://wa.me/"&SUBSTITUTE(SUBSTITUTE(SUBSTITUTE(SUBSTITUTE(SUBSTITUTE(SUBSTITUTE(_xlfn.XLOOKUP($A48,'Item Master'!$A$4:$A$53,'Item Master'!$I$4:$I$53,""),"+",""),"-","")," ",""),"(",""),")",""),".","")&"?text="&SUBSTITUTE("Hello "&_xlfn.XLOOKUP($A48,'Item Master'!$A$4:$A$53,'Item Master'!$H$4:$H$53,"Supplier")&", we urgently need more "&$B48&". Current stock is only "&TEXT($E48,"0")&" units. Please confirm availability and your fastest lead time. Thank you - Momentum Mind Store."," ","%20"),"💬 ORDER NOW"),"")) | H48: =IF($A48="","",IF($F48="⚠️ REORDER NOW",HYPERLINK("mailto:"&_xlfn.XLOOKUP($A48,'Item Master'!$A$4:$A$53,'Item Master'!$J$4:$J$53,"")&"?subject="&SUBSTITUTE("URGENT restock request - "&$B48&" ("&$A48&")"," ","%20")&"&body="&SUBSTITUTE(SUBSTITUTE("Hello "&_xlfn.XLOOKUP($A48,'Item Master'!$A$4:$A$53,'Item Master'!$H$4:$H$53,"Supplier")&"," & CHAR(10) & "We urgently need to restock "&$B48&" (SKU "&$A48&"). Our current stock is "&TEXT($E48,"0")&" units, which is below our reorder threshold." & CHAR(10) & "Please confirm availability, unit price and lead time by return." & CHAR(10) & "Kind regards," & CHAR(10) & "Momentum Mind Store"," ","%20"),CHAR(10),"%0D%0A"),"✉️ EMAIL"),"")) | I48: =IF($A48="","",$E48*_xlfn.XLOOKUP($A48,'Item Master'!$A$4:$A$53,'Item Master'!$D$4:$D$53,0))
A49: =IF(INDEX('Item Master'!$A$4:$A$53,41)="","",INDEX('Item Master'!$A$4:$A$53,41)) | B49: =IF($A49="","",_xlfn.XLOOKUP($A49,'Item Master'!$A$4:$A$53,'Item Master'!$B$4:$B$53,"")) | C49: =IF($A49="","",SUMIFS('Log Transaction'!$E$4:$E$303,'Log Transaction'!$C$4:$C$303,$A49,'Log Transaction'!$D$4:$D$303,"IN")) | D49: =IF($A49="","",SUMIFS('Log Transaction'!$E$4:$E$303,'Log Transaction'!$C$4:$C$303,$A49,'Log Transaction'!$D$4:$D$303,"OUT")+SUMIFS('Log Transaction'!$E$4:$E$303,'Log Transaction'!$C$4:$C$303,$A49,'Log Transaction'!$D$4:$D$303,"SHRINKAGE")) | E49: =IF($A49="","",$C49-$D49) | F49: =IF($A49="","",IF($E49<=_xlfn.XLOOKUP($A49,'Item Master'!$A$4:$A$53,'Item Master'!$F$4:$F$53,0)*0.1,"⚠️ REORDER NOW","✅ IN STOCK")) | G49: =IF($A49="","",IF($F49="⚠️ REORDER NOW",HYPERLINK("https://wa.me/"&SUBSTITUTE(SUBSTITUTE(SUBSTITUTE(SUBSTITUTE(SUBSTITUTE(SUBSTITUTE(_xlfn.XLOOKUP($A49,'Item Master'!$A$4:$A$53,'Item Master'!$I$4:$I$53,""),"+",""),"-","")," ",""),"(",""),")",""),".","")&"?text="&SUBSTITUTE("Hello "&_xlfn.XLOOKUP($A49,'Item Master'!$A$4:$A$53,'Item Master'!$H$4:$H$53,"Supplier")&", we urgently need more "&$B49&". Current stock is only "&TEXT($E49,"0")&" units. Please confirm availability and your fastest lead time. Thank you - Momentum Mind Store."," ","%20"),"💬 ORDER NOW"),"")) | H49: =IF($A49="","",IF($F49="⚠️ REORDER NOW",HYPERLINK("mailto:"&_xlfn.XLOOKUP($A49,'Item Master'!$A$4:$A$53,'Item Master'!$J$4:$J$53,"")&"?subject="&SUBSTITUTE("URGENT restock request - "&$B49&" ("&$A49&")"," ","%20")&"&body="&SUBSTITUTE(SUBSTITUTE("Hello "&_xlfn.XLOOKUP($A49,'Item Master'!$A$4:$A$53,'Item Master'!$H$4:$H$53,"Supplier")&"," & CHAR(10) & "We urgently need to restock "&$B49&" (SKU "&$A49&"). Our current stock is "&TEXT($E49,"0")&" units, which is below our reorder threshold." & CHAR(10) & "Please confirm availability, unit price and lead time by return." & CHAR(10) & "Kind regards," & CHAR(10) & "Momentum Mind Store"," ","%20"),CHAR(10),"%0D%0A"),"✉️ EMAIL"),"")) | I49: =IF($A49="","",$E49*_xlfn.XLOOKUP($A49,'Item Master'!$A$4:$A$53,'Item Master'!$D$4:$D$53,0))
A50: =IF(INDEX('Item Master'!$A$4:$A$53,42)="","",INDEX('Item Master'!$A$4:$A$53,42)) | B50: =IF($A50="","",_xlfn.XLOOKUP($A50,'Item Master'!$A$4:$A$53,'Item Master'!$B$4:$B$53,"")) | C50: =IF($A50="","",SUMIFS('Log Transaction'!$E$4:$E$303,'Log Transaction'!$C$4:$C$303,$A50,'Log Transaction'!$D$4:$D$303,"IN")) | D50: =IF($A50="","",SUMIFS('Log Transaction'!$E$4:$E$303,'Log Transaction'!$C$4:$C$303,$A50,'Log Transaction'!$D$4:$D$303,"OUT")+SUMIFS('Log Transaction'!$E$4:$E$303,'Log Transaction'!$C$4:$C$303,$A50,'Log Transaction'!$D$4:$D$303,"SHRINKAGE")) | E50: =IF($A50="","",$C50-$D50) | F50: =IF($A50="","",IF($E50<=_xlfn.XLOOKUP($A50,'Item Master'!$A$4:$A$53,'Item Master'!$F$4:$F$53,0)*0.1,"⚠️ REORDER NOW","✅ IN STOCK")) | G50: =IF($A50="","",IF($F50="⚠️ REORDER NOW",HYPERLINK("https://wa.me/"&SUBSTITUTE(SUBSTITUTE(SUBSTITUTE(SUBSTITUTE(SUBSTITUTE(SUBSTITUTE(_xlfn.XLOOKUP($A50,'Item Master'!$A$4:$A$53,'Item Master'!$I$4:$I$53,""),"+",""),"-","")," ",""),"(",""),")",""),".","")&"?text="&SUBSTITUTE("Hello "&_xlfn.XLOOKUP($A50,'Item Master'!$A$4:$A$53,'Item Master'!$H$4:$H$53,"Supplier")&", we urgently need more "&$B50&". Current stock is only "&TEXT($E50,"0")&" units. Please confirm availability and your fastest lead time. Thank you - Momentum Mind Store."," ","%20"),"💬 ORDER NOW"),"")) | H50: =IF($A50="","",IF($F50="⚠️ REORDER NOW",HYPERLINK("mailto:"&_xlfn.XLOOKUP($A50,'Item Master'!$A$4:$A$53,'Item Master'!$J$4:$J$53,"")&"?subject="&SUBSTITUTE("URGENT restock request - "&$B50&" ("&$A50&")"," ","%20")&"&body="&SUBSTITUTE(SUBSTITUTE("Hello "&_xlfn.XLOOKUP($A50,'Item Master'!$A$4:$A$53,'Item Master'!$H$4:$H$53,"Supplier")&"," & CHAR(10) & "We urgently need to restock "&$B50&" (SKU "&$A50&"). Our current stock is "&TEXT($E50,"0")&" units, which is below our reorder threshold." & CHAR(10) & "Please confirm availability, unit price and lead time by return." & CHAR(10) & "Kind regards," & CHAR(10) & "Momentum Mind Store"," ","%20"),CHAR(10),"%0D%0A"),"✉️ EMAIL"),"")) | I50: =IF($A50="","",$E50*_xlfn.XLOOKUP($A50,'Item Master'!$A$4:$A$53,'Item Master'!$D$4:$D$53,0))
A51: =IF(INDEX('Item Master'!$A$4:$A$53,43)="","",INDEX('Item Master'!$A$4:$A$53,43)) | B51: =IF($A51="","",_xlfn.XLOOKUP($A51,'Item Master'!$A$4:$A$53,'Item Master'!$B$4:$B$53,"")) | C51: =IF($A51="","",SUMIFS('Log Transaction'!$E$4:$E$303,'Log Transaction'!$C$4:$C$303,$A51,'Log Transaction'!$D$4:$D$303,"IN")) | D51: =IF($A51="","",SUMIFS('Log Transaction'!$E$4:$E$303,'Log Transaction'!$C$4:$C$303,$A51,'Log Transaction'!$D$4:$D$303,"OUT")+SUMIFS('Log Transaction'!$E$4:$E$303,'Log Transaction'!$C$4:$C$303,$A51,'Log Transaction'!$D$4:$D$303,"SHRINKAGE")) | E51: =IF($A51="","",$C51-$D51) | F51: =IF($A51="","",IF($E51<=_xlfn.XLOOKUP($A51,'Item Master'!$A$4:$A$53,'Item Master'!$F$4:$F$53,0)*0.1,"⚠️ REORDER NOW","✅ IN STOCK")) | G51: =IF($A51="","",IF($F51="⚠️ REORDER NOW",HYPERLINK("https://wa.me/"&SUBSTITUTE(SUBSTITUTE(SUBSTITUTE(SUBSTITUTE(SUBSTITUTE(SUBSTITUTE(_xlfn.XLOOKUP($A51,'Item Master'!$A$4:$A$53,'Item Master'!$I$4:$I$53,""),"+",""),"-","")," ",""),"(",""),")",""),".","")&"?text="&SUBSTITUTE("Hello "&_xlfn.XLOOKUP($A51,'Item Master'!$A$4:$A$53,'Item Master'!$H$4:$H$53,"Supplier")&", we urgently need more "&$B51&". Current stock is only "&TEXT($E51,"0")&" units. Please confirm availability and your fastest lead time. Thank you - Momentum Mind Store."," ","%20"),"💬 ORDER NOW"),"")) | H51: =IF($A51="","",IF($F51="⚠️ REORDER NOW",HYPERLINK("mailto:"&_xlfn.XLOOKUP($A51,'Item Master'!$A$4:$A$53,'Item Master'!$J$4:$J$53,"")&"?subject="&SUBSTITUTE("URGENT restock request - "&$B51&" ("&$A51&")"," ","%20")&"&body="&SUBSTITUTE(SUBSTITUTE("Hello "&_xlfn.XLOOKUP($A51,'Item Master'!$A$4:$A$53,'Item Master'!$H$4:$H$53,"Supplier")&"," & CHAR(10) & "We urgently need to restock "&$B51&" (SKU "&$A51&"). Our current stock is "&TEXT($E51,"0")&" units, which is below our reorder threshold." & CHAR(10) & "Please confirm availability, unit price and lead time by return." & CHAR(10) & "Kind regards," & CHAR(10) & "Momentum Mind Store"," ","%20"),CHAR(10),"%0D%0A"),"✉️ EMAIL"),"")) | I51: =IF($A51="","",$E51*_xlfn.XLOOKUP($A51,'Item Master'!$A$4:$A$53,'Item Master'!$D$4:$D$53,0))
A52: =IF(INDEX('Item Master'!$A$4:$A$53,44)="","",INDEX('Item Master'!$A$4:$A$53,44)) | B52: =IF($A52="","",_xlfn.XLOOKUP($A52,'Item Master'!$A$4:$A$53,'Item Master'!$B$4:$B$53,"")) | C52: =IF($A52="","",SUMIFS('Log Transaction'!$E$4:$E$303,'Log Transaction'!$C$4:$C$303,$A52,'Log Transaction'!$D$4:$D$303,"IN")) | D52: =IF($A52="","",SUMIFS('Log Transaction'!$E$4:$E$303,'Log Transaction'!$C$4:$C$303,$A52,'Log Transaction'!$D$4:$D$303,"OUT")+SUMIFS('Log Transaction'!$E$4:$E$303,'Log Transaction'!$C$4:$C$303,$A52,'Log Transaction'!$D$4:$D$303,"SHRINKAGE")) | E52: =IF($A52="","",$C52-$D52) | F52: =IF($A52="","",IF($E52<=_xlfn.XLOOKUP($A52,'Item Master'!$A$4:$A$53,'Item Master'!$F$4:$F$53,0)*0.1,"⚠️ REORDER NOW","✅ IN STOCK")) | G52: =IF($A52="","",IF($F52="⚠️ REORDER NOW",HYPERLINK("https://wa.me/"&SUBSTITUTE(SUBSTITUTE(SUBSTITUTE(SUBSTITUTE(SUBSTITUTE(SUBSTITUTE(_xlfn.XLOOKUP($A52,'Item Master'!$A$4:$A$53,'Item Master'!$I$4:$I$53,""),"+",""),"-","")," ",""),"(",""),")",""),".","")&"?text="&SUBSTITUTE("Hello "&_xlfn.XLOOKUP($A52,'Item Master'!$A$4:$A$53,'Item Master'!$H$4:$H$53,"Supplier")&", we urgently need more "&$B52&". Current stock is only "&TEXT($E52,"0")&" units. Please confirm availability and your fastest lead time. Thank you - Momentum Mind Store."," ","%20"),"💬 ORDER NOW"),"")) | H52: =IF($A52="","",IF($F52="⚠️ REORDER NOW",HYPERLINK("mailto:"&_xlfn.XLOOKUP($A52,'Item Master'!$A$4:$A$53,'Item Master'!$J$4:$J$53,"")&"?subject="&SUBSTITUTE("URGENT restock request - "&$B52&" ("&$A52&")"," ","%20")&"&body="&SUBSTITUTE(SUBSTITUTE("Hello "&_xlfn.XLOOKUP($A52,'Item Master'!$A$4:$A$53,'Item Master'!$H$4:$H$53,"Supplier")&"," & CHAR(10) & "We urgently need to restock "&$B52&" (SKU "&$A52&"). Our current stock is "&TEXT($E52,"0")&" units, which is below our reorder threshold." & CHAR(10) & "Please confirm availability, unit price and lead time by return." & CHAR(10) & "Kind regards," & CHAR(10) & "Momentum Mind Store"," ","%20"),CHAR(10),"%0D%0A"),"✉️ EMAIL"),"")) | I52: =IF($A52="","",$E52*_xlfn.XLOOKUP($A52,'Item Master'!$A$4:$A$53,'Item Master'!$D$4:$D$53,0))
A53: =IF(INDEX('Item Master'!$A$4:$A$53,45)="","",INDEX('Item Master'!$A$4:$A$53,45)) | B53: =IF($A53="","",_xlfn.XLOOKUP($A53,'Item Master'!$A$4:$A$53,'Item Master'!$B$4:$B$53,"")) | C53: =IF($A53="","",SUMIFS('Log Transaction'!$E$4:$E$303,'Log Transaction'!$C$4:$C$303,$A53,'Log Transaction'!$D$4:$D$303,"IN")) | D53: =IF($A53="","",SUMIFS('Log Transaction'!$E$4:$E$303,'Log Transaction'!$C$4:$C$303,$A53,'Log Transaction'!$D$4:$D$303,"OUT")+SUMIFS('Log Transaction'!$E$4:$E$303,'Log Transaction'!$C$4:$C$303,$A53,'Log Transaction'!$D$4:$D$303,"SHRINKAGE")) | E53: =IF($A53="","",$C53-$D53) | F53: =IF($A53="","",IF($E53<=_xlfn.XLOOKUP($A53,'Item Master'!$A$4:$A$53,'Item Master'!$F$4:$F$53,0)*0.1,"⚠️ REORDER NOW","✅ IN STOCK")) | G53: =IF($A53="","",IF($F53="⚠️ REORDER NOW",HYPERLINK("https://wa.me/"&SUBSTITUTE(SUBSTITUTE(SUBSTITUTE(SUBSTITUTE(SUBSTITUTE(SUBSTITUTE(_xlfn.XLOOKUP($A53,'Item Master'!$A$4:$A$53,'Item Master'!$I$4:$I$53,""),"+",""),"-","")," ",""),"(",""),")",""),".","")&"?text="&SUBSTITUTE("Hello "&_xlfn.XLOOKUP($A53,'Item Master'!$A$4:$A$53,'Item Master'!$H$4:$H$53,"Supplier")&", we urgently need more "&$B53&". Current stock is only "&TEXT($E53,"0")&" units. Please confirm availability and your fastest lead time. Thank you - Momentum Mind Store."," ","%20"),"💬 ORDER NOW"),"")) | H53: =IF($A53="","",IF($F53="⚠️ REORDER NOW",HYPERLINK("mailto:"&_xlfn.XLOOKUP($A53,'Item Master'!$A$4:$A$53,'Item Master'!$J$4:$J$53,"")&"?subject="&SUBSTITUTE("URGENT restock request - "&$B53&" ("&$A53&")"," ","%20")&"&body="&SUBSTITUTE(SUBSTITUTE("Hello "&_xlfn.XLOOKUP($A53,'Item Master'!$A$4:$A$53,'Item Master'!$H$4:$H$53,"Supplier")&"," & CHAR(10) & "We urgently need to restock "&$B53&" (SKU "&$A53&"). Our current stock is "&TEXT($E53,"0")&" units, which is below our reorder threshold." & CHAR(10) & "Please confirm availability, unit price and lead time by return." & CHAR(10) & "Kind regards," & CHAR(10) & "Momentum Mind Store"," ","%20"),CHAR(10),"%0D%0A"),"✉️ EMAIL"),"")) | I53: =IF($A53="","",$E53*_xlfn.XLOOKUP($A53,'Item Master'!$A$4:$A$53,'Item Master'!$D$4:$D$53,0))
A54: =IF(INDEX('Item Master'!$A$4:$A$53,46)="","",INDEX('Item Master'!$A$4:$A$53,46)) | B54: =IF($A54="","",_xlfn.XLOOKUP($A54,'Item Master'!$A$4:$A$53,'Item Master'!$B$4:$B$53,"")) | C54: =IF($A54="","",SUMIFS('Log Transaction'!$E$4:$E$303,'Log Transaction'!$C$4:$C$303,$A54,'Log Transaction'!$D$4:$D$303,"IN")) | D54: =IF($A54="","",SUMIFS('Log Transaction'!$E$4:$E$303,'Log Transaction'!$C$4:$C$303,$A54,'Log Transaction'!$D$4:$D$303,"OUT")+SUMIFS('Log Transaction'!$E$4:$E$303,'Log Transaction'!$C$4:$C$303,$A54,'Log Transaction'!$D$4:$D$303,"SHRINKAGE")) | E54: =IF($A54="","",$C54-$D54) | F54: =IF($A54="","",IF($E54<=_xlfn.XLOOKUP($A54,'Item Master'!$A$4:$A$53,'Item Master'!$F$4:$F$53,0)*0.1,"⚠️ REORDER NOW","✅ IN STOCK")) | G54: =IF($A54="","",IF($F54="⚠️ REORDER NOW",HYPERLINK("https://wa.me/"&SUBSTITUTE(SUBSTITUTE(SUBSTITUTE(SUBSTITUTE(SUBSTITUTE(SUBSTITUTE(_xlfn.XLOOKUP($A54,'Item Master'!$A$4:$A$53,'Item Master'!$I$4:$I$53,""),"+",""),"-","")," ",""),"(",""),")",""),".","")&"?text="&SUBSTITUTE("Hello "&_xlfn.XLOOKUP($A54,'Item Master'!$A$4:$A$53,'Item Master'!$H$4:$H$53,"Supplier")&", we urgently need more "&$B54&". Current stock is only "&TEXT($E54,"0")&" units. Please confirm availability and your fastest lead time. Thank you - Momentum Mind Store."," ","%20"),"💬 ORDER NOW"),"")) | H54: =IF($A54="","",IF($F54="⚠️ REORDER NOW",HYPERLINK("mailto:"&_xlfn.XLOOKUP($A54,'Item Master'!$A$4:$A$53,'Item Master'!$J$4:$J$53,"")&"?subject="&SUBSTITUTE("URGENT restock request - "&$B54&" ("&$A54&")"," ","%20")&"&body="&SUBSTITUTE(SUBSTITUTE("Hello "&_xlfn.XLOOKUP($A54,'Item Master'!$A$4:$A$53,'Item Master'!$H$4:$H$53,"Supplier")&"," & CHAR(10) & "We urgently need to restock "&$B54&" (SKU "&$A54&"). Our current stock is "&TEXT($E54,"0")&" units, which is below our reorder threshold." & CHAR(10) & "Please confirm availability, unit price and lead time by return." & CHAR(10) & "Kind regards," & CHAR(10) & "Momentum Mind Store"," ","%20"),CHAR(10),"%0D%0A"),"✉️ EMAIL"),"")) | I54: =IF($A54="","",$E54*_xlfn.XLOOKUP($A54,'Item Master'!$A$4:$A$53,'Item Master'!$D$4:$D$53,0))
A55: =IF(INDEX('Item Master'!$A$4:$A$53,47)="","",INDEX('Item Master'!$A$4:$A$53,47)) | B55: =IF($A55="","",_xlfn.XLOOKUP($A55,'Item Master'!$A$4:$A$53,'Item Master'!$B$4:$B$53,"")) | C55: =IF($A55="","",SUMIFS('Log Transaction'!$E$4:$E$303,'Log Transaction'!$C$4:$C$303,$A55,'Log Transaction'!$D$4:$D$303,"IN")) | D55: =IF($A55="","",SUMIFS('Log Transaction'!$E$4:$E$303,'Log Transaction'!$C$4:$C$303,$A55,'Log Transaction'!$D$4:$D$303,"OUT")+SUMIFS('Log Transaction'!$E$4:$E$303,'Log Transaction'!$C$4:$C$303,$A55,'Log Transaction'!$D$4:$D$303,"SHRINKAGE")) | E55: =IF($A55="","",$C55-$D55) | F55: =IF($A55="","",IF($E55<=_xlfn.XLOOKUP($A55,'Item Master'!$A$4:$A$53,'Item Master'!$F$4:$F$53,0)*0.1,"⚠️ REORDER NOW","✅ IN STOCK")) | G55: =IF($A55="","",IF($F55="⚠️ REORDER NOW",HYPERLINK("https://wa.me/"&SUBSTITUTE(SUBSTITUTE(SUBSTITUTE(SUBSTITUTE(SUBSTITUTE(SUBSTITUTE(_xlfn.XLOOKUP($A55,'Item Master'!$A$4:$A$53,'Item Master'!$I$4:$I$53,""),"+",""),"-","")," ",""),"(",""),")",""),".","")&"?text="&SUBSTITUTE("Hello "&_xlfn.XLOOKUP($A55,'Item Master'!$A$4:$A$53,'Item Master'!$H$4:$H$53,"Supplier")&", we urgently need more "&$B55&". Current stock is only "&TEXT($E55,"0")&" units. Please confirm availability and your fastest lead time. Thank you - Momentum Mind Store."," ","%20"),"💬 ORDER NOW"),"")) | H55: =IF($A55="","",IF($F55="⚠️ REORDER NOW",HYPERLINK("mailto:"&_xlfn.XLOOKUP($A55,'Item Master'!$A$4:$A$53,'Item Master'!$J$4:$J$53,"")&"?subject="&SUBSTITUTE("URGENT restock request - "&$B55&" ("&$A55&")"," ","%20")&"&body="&SUBSTITUTE(SUBSTITUTE("Hello "&_xlfn.XLOOKUP($A55,'Item Master'!$A$4:$A$53,'Item Master'!$H$4:$H$53,"Supplier")&"," & CHAR(10) & "We urgently need to restock "&$B55&" (SKU "&$A55&"). Our current stock is "&TEXT($E55,"0")&" units, which is below our reorder threshold." & CHAR(10) & "Please confirm availability, unit price and lead time by return." & CHAR(10) & "Kind regards," & CHAR(10) & "Momentum Mind Store"," ","%20"),CHAR(10),"%0D%0A"),"✉️ EMAIL"),"")) | I55: =IF($A55="","",$E55*_xlfn.XLOOKUP($A55,'Item Master'!$A$4:$A$53,'Item Master'!$D$4:$D$53,0))
A56: =IF(INDEX('Item Master'!$A$4:$A$53,48)="","",INDEX('Item Master'!$A$4:$A$53,48)) | B56: =IF($A56="","",_xlfn.XLOOKUP($A56,'Item Master'!$A$4:$A$53,'Item Master'!$B$4:$B$53,"")) | C56: =IF($A56="","",SUMIFS('Log Transaction'!$E$4:$E$303,'Log Transaction'!$C$4:$C$303,$A56,'Log Transaction'!$D$4:$D$303,"IN")) | D56: =IF($A56="","",SUMIFS('Log Transaction'!$E$4:$E$303,'Log Transaction'!$C$4:$C$303,$A56,'Log Transaction'!$D$4:$D$303,"OUT")+SUMIFS('Log Transaction'!$E$4:$E$303,'Log Transaction'!$C$4:$C$303,$A56,'Log Transaction'!$D$4:$D$303,"SHRINKAGE")) | E56: =IF($A56="","",$C56-$D56) | F56: =IF($A56="","",IF($E56<=_xlfn.XLOOKUP($A56,'Item Master'!$A$4:$A$53,'Item Master'!$F$4:$F$53,0)*0.1,"⚠️ REORDER NOW","✅ IN STOCK")) | G56: =IF($A56="","",IF($F56="⚠️ REORDER NOW",HYPERLINK("https://wa.me/"&SUBSTITUTE(SUBSTITUTE(SUBSTITUTE(SUBSTITUTE(SUBSTITUTE(SUBSTITUTE(_xlfn.XLOOKUP($A56,'Item Master'!$A$4:$A$53,'Item Master'!$I$4:$I$53,""),"+",""),"-","")," ",""),"(",""),")",""),".","")&"?text="&SUBSTITUTE("Hello "&_xlfn.XLOOKUP($A56,'Item Master'!$A$4:$A$53,'Item Master'!$H$4:$H$53,"Supplier")&", we urgently need more "&$B56&". Current stock is only "&TEXT($E56,"0")&" units. Please confirm availability and your fastest lead time. Thank you - Momentum Mind Store."," ","%20"),"💬 ORDER NOW"),"")) | H56: =IF($A56="","",IF($F56="⚠️ REORDER NOW",HYPERLINK("mailto:"&_xlfn.XLOOKUP($A56,'Item Master'!$A$4:$A$53,'Item Master'!$J$4:$J$53,"")&"?subject="&SUBSTITUTE("URGENT restock request - "&$B56&" ("&$A56&")"," ","%20")&"&body="&SUBSTITUTE(SUBSTITUTE("Hello "&_xlfn.XLOOKUP($A56,'Item Master'!$A$4:$A$53,'Item Master'!$H$4:$H$53,"Supplier")&"," & CHAR(10) & "We urgently need to restock "&$B56&" (SKU "&$A56&"). Our current stock is "&TEXT($E56,"0")&" units, which is below our reorder threshold." & CHAR(10) & "Please confirm availability, unit price and lead time by return." & CHAR(10) & "Kind regards," & CHAR(10) & "Momentum Mind Store"," ","%20"),CHAR(10),"%0D%0A"),"✉️ EMAIL"),"")) | I56: =IF($A56="","",$E56*_xlfn.XLOOKUP($A56,'Item Master'!$A$4:$A$53,'Item Master'!$D$4:$D$53,0))
A57: =IF(INDEX('Item Master'!$A$4:$A$53,49)="","",INDEX('Item Master'!$A$4:$A$53,49)) | B57: =IF($A57="","",_xlfn.XLOOKUP($A57,'Item Master'!$A$4:$A$53,'Item Master'!$B$4:$B$53,"")) | C57: =IF($A57="","",SUMIFS('Log Transaction'!$E$4:$E$303,'Log Transaction'!$C$4:$C$303,$A57,'Log Transaction'!$D$4:$D$303,"IN")) | D57: =IF($A57="","",SUMIFS('Log Transaction'!$E$4:$E$303,'Log Transaction'!$C$4:$C$303,$A57,'Log Transaction'!$D$4:$D$303,"OUT")+SUMIFS('Log Transaction'!$E$4:$E$303,'Log Transaction'!$C$4:$C$303,$A57,'Log Transaction'!$D$4:$D$303,"SHRINKAGE")) | E57: =IF($A57="","",$C57-$D57) | F57: =IF($A57="","",IF($E57<=_xlfn.XLOOKUP($A57,'Item Master'!$A$4:$A$53,'Item Master'!$F$4:$F$53,0)*0.1,"⚠️ REORDER NOW","✅ IN STOCK")) | G57: =IF($A57="","",IF($F57="⚠️ REORDER NOW",HYPERLINK("https://wa.me/"&SUBSTITUTE(SUBSTITUTE(SUBSTITUTE(SUBSTITUTE(SUBSTITUTE(SUBSTITUTE(_xlfn.XLOOKUP($A57,'Item Master'!$A$4:$A$53,'Item Master'!$I$4:$I$53,""),"+",""),"-","")," ",""),"(",""),")",""),".","")&"?text="&SUBSTITUTE("Hello "&_xlfn.XLOOKUP($A57,'Item Master'!$A$4:$A$53,'Item Master'!$H$4:$H$53,"Supplier")&", we urgently need more "&$B57&". Current stock is only "&TEXT($E57,"0")&" units. Please confirm availability and your fastest lead time. Thank you - Momentum Mind Store."," ","%20"),"💬 ORDER NOW"),"")) | H57: =IF($A57="","",IF($F57="⚠️ REORDER NOW",HYPERLINK("mailto:"&_xlfn.XLOOKUP($A57,'Item Master'!$A$4:$A$53,'Item Master'!$J$4:$J$53,"")&"?subject="&SUBSTITUTE("URGENT restock request - "&$B57&" ("&$A57&")"," ","%20")&"&body="&SUBSTITUTE(SUBSTITUTE("Hello "&_xlfn.XLOOKUP($A57,'Item Master'!$A$4:$A$53,'Item Master'!$H$4:$H$53,"Supplier")&"," & CHAR(10) & "We urgently need to restock "&$B57&" (SKU "&$A57&"). Our current stock is "&TEXT($E57,"0")&" units, which is below our reorder threshold." & CHAR(10) & "Please confirm availability, unit price and lead time by return." & CHAR(10) & "Kind regards," & CHAR(10) & "Momentum Mind Store"," ","%20"),CHAR(10),"%0D%0A"),"✉️ EMAIL"),"")) | I57: =IF($A57="","",$E57*_xlfn.XLOOKUP($A57,'Item Master'!$A$4:$A$53,'Item Master'!$D$4:$D$53,0))
A58: =IF(INDEX('Item Master'!$A$4:$A$53,50)="","",INDEX('Item Master'!$A$4:$A$53,50)) | B58: =IF($A58="","",_xlfn.XLOOKUP($A58,'Item Master'!$A$4:$A$53,'Item Master'!$B$4:$B$53,"")) | C58: =IF($A58="","",SUMIFS('Log Transaction'!$E$4:$E$303,'Log Transaction'!$C$4:$C$303,$A58,'Log Transaction'!$D$4:$D$303,"IN")) | D58: =IF($A58="","",SUMIFS('Log Transaction'!$E$4:$E$303,'Log Transaction'!$C$4:$C$303,$A58,'Log Transaction'!$D$4:$D$303,"OUT")+SUMIFS('Log Transaction'!$E$4:$E$303,'Log Transaction'!$C$4:$C$303,$A58,'Log Transaction'!$D$4:$D$303,"SHRINKAGE")) | E58: =IF($A58="","",$C58-$D58) | F58: =IF($A58="","",IF($E58<=_xlfn.XLOOKUP($A58,'Item Master'!$A$4:$A$53,'Item Master'!$F$4:$F$53,0)*0.1,"⚠️ REORDER NOW","✅ IN STOCK")) | G58: =IF($A58="","",IF($F58="⚠️ REORDER NOW",HYPERLINK("https://wa.me/"&SUBSTITUTE(SUBSTITUTE(SUBSTITUTE(SUBSTITUTE(SUBSTITUTE(SUBSTITUTE(_xlfn.XLOOKUP($A58,'Item Master'!$A$4:$A$53,'Item Master'!$I$4:$I$53,""),"+",""),"-","")," ",""),"(",""),")",""),".","")&"?text="&SUBSTITUTE("Hello "&_xlfn.XLOOKUP($A58,'Item Master'!$A$4:$A$53,'Item Master'!$H$4:$H$53,"Supplier")&", we urgently need more "&$B58&". Current stock is only "&TEXT($E58,"0")&" units. Please confirm availability and your fastest lead time. Thank you - Momentum Mind Store."," ","%20"),"💬 ORDER NOW"),"")) | H58: =IF($A58="","",IF($F58="⚠️ REORDER NOW",HYPERLINK("mailto:"&_xlfn.XLOOKUP($A58,'Item Master'!$A$4:$A$53,'Item Master'!$J$4:$J$53,"")&"?subject="&SUBSTITUTE("URGENT restock request - "&$B58&" ("&$A58&")"," ","%20")&"&body="&SUBSTITUTE(SUBSTITUTE("Hello "&_xlfn.XLOOKUP($A58,'Item Master'!$A$4:$A$53,'Item Master'!$H$4:$H$53,"Supplier")&"," & CHAR(10) & "We urgently need to restock "&$B58&" (SKU "&$A58&"). Our current stock is "&TEXT($E58,"0")&" units, which is below our reorder threshold." & CHAR(10) & "Please confirm availability, unit price and lead time by return." & CHAR(10) & "Kind regards," & CHAR(10) & "Momentum Mind Store"," ","%20"),CHAR(10),"%0D%0A"),"✉️ EMAIL"),"")) | I58: =IF($A58="","",$E58*_xlfn.XLOOKUP($A58,'Item Master'!$A$4:$A$53,'Item Master'!$D$4:$D$53,0))

Sheet Item Master
A1: =HYPERLINK("#'Dashboard'!A1","🏠 Dashboard") | C1: =HYPERLINK("#'Item Master'!A1","📦 Products") | E1: =HYPERLINK("#'Log Transaction'!A1","✍️ Log Sale") | G1: =HYPERLINK("#'Invoice Generator'!A1","🧾 Invoice") | I1: =HYPERLINK("#'Start Here'!A1","🚀 Start Here")
A3: SKU | B3: 📦 Product Name | C3: Category | D3: Cost | E3: Price | F3: Max Stock | G3: Reorder Point | H3: Supplier Name | I3: 📞 Supp. Phone | J3: ✉️ Supp. Email
A4: LAV-001 | B4: 🕯️ Lavender Soy Candle 220g | C4: Home Fragrance | D4: 6.5 | E4: 18 | F4: 120 | G4: 25 | H4: Aurora Wax Co. | I4: 15551234567 | J4: orders@aurorawax.com
A5: CER-014 | B5: ☕ Ceramic Mug — Sand | C5: Drinkware | D5: 4.2 | E5: 14 | F5: 200 | G5: 40 | H5: Kiln & Clay Ltd | I5: 15559876543 | J5: sales@kilnclay.com
A6: TOT-007 | B6: 👜 Canvas Tote Bag — Natural | C6: Bags | D6: 3.8 | E6: 12.5 | F6: 150 | G6: 30 | H6: NorthLoom Textiles | I6: 15554567890 | J6: hello@northloom.com
A7: JRN-002 | B7: 📓 Linen Journal A5 | C7: Stationery | D7: 5.1 | E7: 16 | F7: 100 | G7: 20 | H7: PaperFold Studio | I7: 15553216549 | J7: supply@paperfold.com
A8: SKN-021 | B8: 🧴 Botanical Body Oil 100ml | C8: Skincare | D8: 7.9 | E8: 24 | F8: 80 | G8: 16 | H8: Botanica Labs | I8: 15557778888 | J8: orders@botanicalabs.com
A9: TEA-009 | B9: 🍵 Loose Leaf Tea 200g | C9: Pantry | D9: 5.6 | E9: 17.5 | F9: 90 | G9: 18 | H9: Verde Leaf Imports | I9: 15552223333 | J9: buy@verdeleaf.com

Sheet Log Transaction
A1: =HYPERLINK("#'Dashboard'!A1","🏠 Dashboard") | B1: =HYPERLINK("#'Item Master'!A1","📦 Products") | C1: =HYPERLINK("#'Log Transaction'!A1","✍️ Log Sale") | D1: =HYPERLINK("#'Invoice Generator'!A1","🧾 Invoice") | F1: =HYPERLINK("#'Start Here'!A1","🚀 Start Here")
A3: 📅 Date | B3: 🆔 ID | C3: 🏷️ SKU | D3: 🔄 Type | E3: 🔢 Qty | F3: 💵 Total | G3: Line Key
A4: 46235 | B4: PO-2001 | C4: LAV-001 | D4: IN | E4: 100 | F4: =IF($C4="","",IF($D4="IN",$E4*_xlfn.XLOOKUP($C4,'Item Master'!$A$4:$A$53,'Item Master'!$D$4:$D$53,0),$E4*_xlfn.XLOOKUP($C4,'Item Master'!$A$4:$A$53,'Item Master'!$E$4:$E$53,0))) | G4: =IF($B4="","",IF($D4="OUT",$B4&"|"&COUNTIFS($B$4:$B4,$B4,$D$4:$D4,"OUT"),""))
A5: 46235 | B5: PO-2001 | C5: CER-014 | D5: IN | E5: 150 | F5: =IF($C5="","",IF($D5="IN",$E5*_xlfn.XLOOKUP($C5,'Item Master'!$A$4:$A$53,'Item Master'!$D$4:$D$53,0),$E5*_xlfn.XLOOKUP($C5,'Item Master'!$A$4:$A$53,'Item Master'!$E$4:$E$53,0))) | G5: =IF($B5="","",IF($D5="OUT",$B5&"|"&COUNTIFS($B$4:$B5,$B5,$D$4:$D5,"OUT"),""))
A6: 46235 | B6: PO-2002 | C6: TOT-007 | D6: IN | E6: 120 | F6: =IF($C6="","",IF($D6="IN",$E6*_xlfn.XLOOKUP($C6,'Item Master'!$A$4:$A$53,'Item Master'!$D$4:$D$53,0),$E6*_xlfn.XLOOKUP($C6,'Item Master'!$A$4:$A$53,'Item Master'!$E$4:$E$53,0))) | G6: =IF($B6="","",IF($D6="OUT",$B6&"|"&COUNTIFS($B$4:$B6,$B6,$D$4:$D6,"OUT"),""))
A7: 46236 | B7: PO-2002 | C7: JRN-002 | D7: IN | E7: 80 | F7: =IF($C7="","",IF($D7="IN",$E7*_xlfn.XLOOKUP($C7,'Item Master'!$A$4:$A$53,'Item Master'!$D$4:$D$53,0),$E7*_xlfn.XLOOKUP($C7,'Item Master'!$A$4:$A$53,'Item Master'!$E$4:$E$53,0))) | G7: =IF($B7="","",IF($D7="OUT",$B7&"|"&COUNTIFS($B$4:$B7,$B7,$D$4:$D7,"OUT"),""))
A8: 46236 | B8: PO-2003 | C8: SKN-021 | D8: IN | E8: 60 | F8: =IF($C8="","",IF($D8="IN",$E8*_xlfn.XLOOKUP($C8,'Item Master'!$A$4:$A$53,'Item Master'!$D$4:$D$53,0),$E8*_xlfn.XLOOKUP($C8,'Item Master'!$A$4:$A$53,'Item Master'!$E$4:$E$53,0))) | G8: =IF($B8="","",IF($D8="OUT",$B8&"|"&COUNTIFS($B$4:$B8,$B8,$D$4:$D8,"OUT"),""))
A9: 46236 | B9: PO-2003 | C9: TEA-009 | D9: IN | E9: 70 | F9: =IF($C9="","",IF($D9="IN",$E9*_xlfn.XLOOKUP($C9,'Item Master'!$A$4:$A$53,'Item Master'!$D$4:$D$53,0),$E9*_xlfn.XLOOKUP($C9,'Item Master'!$A$4:$A$53,'Item Master'!$E$4:$E$53,0))) | G9: =IF($B9="","",IF($D9="OUT",$B9&"|"&COUNTIFS($B$4:$B9,$B9,$D$4:$D9,"OUT"),""))
A10: 46239 | B10: INV-1001 | C10: LAV-001 | D10: OUT | E10: 2 | F10: =IF($C10="","",IF($D10="IN",$E10*_xlfn.XLOOKUP($C10,'Item Master'!$A$4:$A$53,'Item Master'!$D$4:$D$53,0),$E10*_xlfn.XLOOKUP($C10,'Item Master'!$A$4:$A$53,'Item Master'!$E$4:$E$53,0))) | G10: =IF($B10="","",IF($D10="OUT",$B10&"|"&COUNTIFS($B$4:$B10,$B10,$D$4:$D10,"OUT"),""))
A11: 46239 | B11: INV-1001 | C11: CER-014 | D11: OUT | E11: 3 | F11: =IF($C11="","",IF($D11="IN",$E11*_xlfn.XLOOKUP($C11,'Item Master'!$A$4:$A$53,'Item Master'!$D$4:$D$53,0),$E11*_xlfn.XLOOKUP($C11,'Item Master'!$A$4:$A$53,'Item Master'!$E$4:$E$53,0))) | G11: =IF($B11="","",IF($D11="OUT",$B11&"|"&COUNTIFS($B$4:$B11,$B11,$D$4:$D11,"OUT"),""))
A12: 46239 | B12: INV-1001 | C12: JRN-002 | D12: OUT | E12: 1 | F12: =IF($C12="","",IF($D12="IN",$E12*_xlfn.XLOOKUP($C12,'Item Master'!$A$4:$A$53,'Item Master'!$D$4:$D$53,0),$E12*_xlfn.XLOOKUP($C12,'Item Master'!$A$4:$A$53,'Item Master'!$E$4:$E$53,0))) | G12: =IF($B12="","",IF($D12="OUT",$B12&"|"&COUNTIFS($B$4:$B12,$B12,$D$4:$D12,"OUT"),""))
A13: 46241 | B13: INV-1002 | C13: TOT-007 | D13: OUT | E13: 4 | F13: =IF($C13="","",IF($D13="IN",$E13*_xlfn.XLOOKUP($C13,'Item Master'!$A$4:$A$53,'Item Master'!$D$4:$D$53,0),$E13*_xlfn.XLOOKUP($C13,'Item Master'!$A$4:$A$53,'Item Master'!$E$4:$E$53,0))) | G13: =IF($B13="","",IF($D13="OUT",$B13&"|"&COUNTIFS($B$4:$B13,$B13,$D$4:$D13,"OUT"),""))
A14: 46241 | B14: INV-1002 | C14: TEA-009 | D14: OUT | E14: 2 | F14: =IF($C14="","",IF($D14="IN",$E14*_xlfn.XLOOKUP($C14,'Item Master'!$A$4:$A$53,'Item Master'!$D$4:$D$53,0),$E14*_xlfn.XLOOKUP($C14,'Item Master'!$A$4:$A$53,'Item Master'!$E$4:$E$53,0))) | G14: =IF($B14="","",IF($D14="OUT",$B14&"|"&COUNTIFS($B$4:$B14,$B14,$D$4:$D14,"OUT"),""))
A15: 46243 | B15: INV-1003 | C15: SKN-021 | D15: OUT | E15: 55 | F15: =IF($C15="","",IF($D15="IN",$E15*_xlfn.XLOOKUP($C15,'Item Master'!$A$4:$A$53,'Item Master'!$D$4:$D$53,0),$E15*_xlfn.XLOOKUP($C15,'Item Master'!$A$4:$A$53,'Item Master'!$E$4:$E$53,0))) | G15: =IF($B15="","",IF($D15="OUT",$B15&"|"&COUNTIFS($B$4:$B15,$B15,$D$4:$D15,"OUT"),""))
... A18: 46246 | B18: INV-1005 | C18: CER-014 | D18: OUT | E18: 12 | F18: =IF($C18="","",IF($D18="IN",$E18*_xlfn.XLOOKUP($C18,'Item Master'!$A$4:$A$53,'Item Master'!$D$4:$D$53,0),$E18*_xlfn.XLOOKUP($C18,'Item Master'!$A$4:$A$53,'Item Master'!$E$4:$E$53,0))) | G18: =IF($B18="","",IF($D18="OUT",$B18&"|"&COUNTIFS($B$4:$B18,$B18,$D$4:$D18,"OUT"),""))
F19: =IF($C19="","",IF($D19="IN",$E19*_xlfn.XLOOKUP($C19,'Item Master'!$A$4:$A$53,'Item Master'!$D$4:$D$53,0),$E19*_xlfn.XLOOKUP($C19,'Item Master'!$A$4:$A$53,'Item Master'!$E$4:$E$53,0))) | G19: =IF($B19="","",IF($D19="OUT",$B19&"|"&COUNTIFS($B$4:$B19,$B19,$D$4:$D19,"OUT"),""))
F20: =IF($C20="","",IF($D20="IN",$E20*_xlfn.XLOOKUP($C20,'Item Master'!$A$4:$A$53,'Item Master'!$D$4:$D$53,0),$E20*_xlfn.XLOOKUP($C20,'Item Master'!$A$4:$A$53,'Item Master'!$E$4:$E$53,0))) | G20: =IF($B20="","",IF($D20="OUT",$B20&"|"&COUNTIFS($B$4:$B20,$B20,$D$4:$D20,"OUT"),""))
F21: =IF($C21="","",IF($D21="IN",$E21*_xlfn.XLOOKUP($C21,'Item Master'!$A$4:$A$53,'Item Master'!$D$4:$D$53,0),$E21*_xlfn.XLOOKUP($C21,'Item Master'!$A$4:$A$53,'Item Master'!$E$4:$E$53,0))) | G21: =IF($B21="","",IF($D21="OUT",$B21&"|"&COUNTIFS($B$4:$B21,$B21,$D$4:$D21,"OUT"),""))
F22: =IF($C22="","",IF($D22="IN",$E22*_xlfn.XLOOKUP($C22,'Item Master'!$A$4:$A$53,'Item Master'!$D$4:$D$53,0),$E22*_xlfn.XLOOKUP($C22,'Item Master'!$A$4:$A$53,'Item Master'!$E$4:$E$53,0))) | G22: =IF($B22="","",IF($D22="OUT",$B22&"|"&COUNTIFS($B$4:$B22,$B22,$D$4:$D22,"OUT"),""))
F23: =IF($C23="","",IF($D23="IN",$E23*_xlfn.XLOOKUP($C23,'Item Master'!$A$4:$A$53,'Item Master'!$D$4:$D$53,0),$E23*_xlfn.XLOOKUP($C23,'Item Master'!$A$4:$A$53,'Item Master'!$E$4:$E$53,0))) | G23: =IF($B23="","",IF($D23="OUT",$B23&"|"&COUNTIFS($B$4:$B23,$B23,$D$4:$D23,"OUT"),""))
F24: =IF($C24="","",IF($D24="IN",$E24*_xlfn.XLOOKUP($C24,'Item Master'!$A$4:$A$53,'Item Master'!$D$4:$D$53,0),$E24*_xlfn.XLOOKUP($C24,'Item Master'!$A$4:$A$53,'Item Master'!$E$4:$E$53,0))) | G24: =IF($B24="","",IF($D24="OUT",$B24&"|"&COUNTIFS($B$4:$B24,$B24,$D$4:$D24,"OUT"),""))
F25: =IF($C25="","",IF($D25="IN",$E25*_xlfn.XLOOKUP($C25,'Item Master'!$A$4:$A$53,'Item Master'!$D$4:$D$53,0),$E25*_xlfn.XLOOKUP($C25,'Item Master'!$A$4:$A$53,'Item Master'!$E$4:$E$53,0))) | G25: =IF($B25="","",IF($D25="OUT",$B25&"|"&COUNTIFS($B$4:$B25,$B25,$D$4:$D25,"OUT"),""))
F26: =IF($C26="","",IF($D26="IN",$E26*_xlfn.XLOOKUP($C26,'Item Master'!$A$4:$A$53,'Item Master'!$D$4:$D$53,0),$E26*_xlfn.XLOOKUP($C26,'Item Master'!$A$4:$A$53,'Item Master'!$E$4:$E$53,0))) | G26: =IF($B26="","",IF($D26="OUT",$B26&"|"&COUNTIFS($B$4:$B26,$B26,$D$4:$D26,"OUT"),""))
F27: =IF($C27="","",IF($D27="IN",$E27*_xlfn.XLOOKUP($C27,'Item Master'!$A$4:$A$53,'Item Master'!$D$4:$D$53,0),$E27*_xlfn.XLOOKUP($C27,'Item Master'!$A$4:$A$53,'Item Master'!$E$4:$E$53,0))) | G27: =IF($B27="","",IF($D27="OUT",$B27&"|"&COUNTIFS($B$4:$B27,$B27,$D$4:$D27,"OUT"),""))
F28: =IF($C28="","",IF($D28="IN",$E28*_xlfn.XLOOKUP($C28,'Item Master'!$A$4:$A$53,'Item Master'!$D$4:$D$53,0),$E28*_xlfn.XLOOKUP($C28,'Item Master'!$A$4:$A$53,'Item Master'!$E$4:$E$53,0))) | G28: =IF($B28="","",IF($D28="OUT",$B28&"|"&COUNTIFS($B$4:$B28,$B28,$D$4:$D28,"OUT"),""))
F29: =IF($C29="","",IF($D29="IN",$E29*_xlfn.XLOOKUP($C29,'Item Master'!$A$4:$A$53,'Item Master'!$D$4:$D$53,0),$E29*_xlfn.XLOOKUP($C29,'Item Master'!$A$4:$A$53,'Item Master'!$E$4:$E$53,0))) | G29: =IF($B29="","",IF($D29="OUT",$B29&"|"&COUNTIFS($B$4:$B29,$B29,$D$4:$D29,"OUT"),""))
F30: =IF($C30="","",IF($D30="IN",$E30*_xlfn.XLOOKUP($C30,'Item Master'!$A$4:$A$53,'Item Master'!$D$4:$D$53,0),$E30*_xlfn.XLOOKUP($C30,'Item Master'!$A$4:$A$53,'Item Master'!$E$4:$E$53,0))) | G30: =IF($B30="","",IF($D30="OUT",$B30&"|"&COUNTIFS($B$4:$B30,$B30,$D$4:$D30,"OUT"),""))
... F303: =IF($C303="","",IF($D303="IN",$E303*_xlfn.XLOOKUP($C303,'Item Master'!$A$4:$A$53,'Item Master'!$D$4:$D$53,0),$E303*_xlfn.XLOOKUP($C303,'Item Master'!$A$4:$A$53,'Item Master'!$E$4:$E$53,0))) | G303: =IF($B303="","",IF($D303="OUT",$B303&"|"&COUNTIFS($B$4:$B303,$B303,$D$4:$D303,"OUT"),""))

Sheet Invoice Generator
A1: =HYPERLINK("#'Dashboard'!A1","🏠 Dashboard") | B1: =HYPERLINK("#'Item Master'!A1","📦 Products") | C1: =HYPERLINK("#'Log Transaction'!A1","✍️ Log Sale") | E1: =HYPERLINK("#'Invoice Generator'!A1","🧾 Invoice") | F1: =HYPERLINK("#'Start Here'!A1","🚀 Start Here")
A4: =Settings!$C$8 | D4: 🧾 INVOICE
A5: =Settings!$C$9&" · "&Settings!$C$10
A7: 🔎 TRANSACTION ID | B7: INV-1001 | D7: Invoice No. | E7: =IF($B$7="","",Settings!$C$14&$B$7)
A8: 📅 DATE | B8: =IFERROR(INDEX('Log Transaction'!$A$4:$A$303,MATCH($B$7,'Log Transaction'!$B$4:$B$303,0)),TODAY()) | D8: Due | E8: =IF($B$8="","",$B$8+Settings!$C$15)
A9: 👤 BILL TO | B9: Customer name · email · address
A11: SKU | B11: 📦 Description | C11: Qty | D11: Unit Price | E11: Line Total
A12: =IFERROR(INDEX('Log Transaction'!$C$4:$C$303,MATCH($B$7&"|"&1,'Log Transaction'!$G$4:$G$303,0)),"") | B12: =IF($A12="","",_xlfn.XLOOKUP($A12,'Item Master'!$A$4:$A$53,'Item Master'!$B$4:$B$53,"")) | C12: =IFERROR(INDEX('Log Transaction'!$E$4:$E$303,MATCH($B$7&"|"&1,'Log Transaction'!$G$4:$G$303,0)),"") | D12: =IF($A12="","",_xlfn.XLOOKUP($A12,'Item Master'!$A$4:$A$53,'Item Master'!$E$4:$E$53,0)) | E12: =IF($A12="","",$C12*$D12)
A13: =IFERROR(INDEX('Log Transaction'!$C$4:$C$303,MATCH($B$7&"|"&2,'Log Transaction'!$G$4:$G$303,0)),"") | B13: =IF($A13="","",_xlfn.XLOOKUP($A13,'Item Master'!$A$4:$A$53,'Item Master'!$B$4:$B$53,"")) | C13: =IFERROR(INDEX('Log Transaction'!$E$4:$E$303,MATCH($B$7&"|"&2,'Log Transaction'!$G$4:$G$303,0)),"") | D13: =IF($A13="","",_xlfn.XLOOKUP($A13,'Item Master'!$A$4:$A$53,'Item Master'!$E$4:$E$53,0)) | E13: =IF($A13="","",$C13*$D13)
A14: =IFERROR(INDEX('Log Transaction'!$C$4:$C$303,MATCH($B$7&"|"&3,'Log Transaction'!$G$4:$G$303,0)),"") | B14: =IF($A14="","",_xlfn.XLOOKUP($A14,'Item Master'!$A$4:$A$53,'Item Master'!$B$4:$B$53,"")) | C14: =IFERROR(INDEX('Log Transaction'!$E$4:$E$303,MATCH($B$7&"|"&3,'Log Transaction'!$G$4:$G$303,0)),"") | D14: =IF($A14="","",_xlfn.XLOOKUP($A14,'Item Master'!$A$4:$A$53,'Item Master'!$E$4:$E$53,0)) | E14: =IF($A14="","",$C14*$D14)
A15: =IFERROR(INDEX('Log Transaction'!$C$4:$C$303,MATCH($B$7&"|"&4,'Log Transaction'!$G$4:$G$303,0)),"") | B15: =IF($A15="","",_xlfn.XLOOKUP($A15,'Item Master'!$A$4:$A$53,'Item Master'!$B$4:$B$53,"")) | C15: =IFERROR(INDEX('Log Transaction'!$E$4:$E$303,MATCH($B$7&"|"&4,'Log Transaction'!$G$4:$G$303,0)),"") | D15: =IF($A15="","",_xlfn.XLOOKUP($A15,'Item Master'!$A$4:$A$53,'Item Master'!$E$4:$E$53,0)) | E15: =IF($A15="","",$C15*$D15)
A16: =IFERROR(INDEX('Log Transaction'!$C$4:$C$303,MATCH($B$7&"|"&5,'Log Transaction'!$G$4:$G$303,0)),"") | B16: =IF($A16="","",_xlfn.XLOOKUP($A16,'Item Master'!$A$4:$A$53,'Item Master'!$B$4:$B$53,"")) | C16: =IFERROR(INDEX('Log Transaction'!$E$4:$E$303,MATCH($B$7&"|"&5,'Log Transaction'!$G$4:$G$303,0)),"") | D16: =IF($A16="","",_xlfn.XLOOKUP($A16,'Item Master'!$A$4:$A$53,'Item Master'!$E$4:$E$53,0)) | E16: =IF($A16="","",$C16*$D16)
A17: =IFERROR(INDEX('Log Transaction'!$C$4:$C$303,MATCH($B$7&"|"&6,'Log Transaction'!$G$4:$G$303,0)),"") | B17: =IF($A17="","",_xlfn.XLOOKUP($A17,'Item Master'!$A$4:$A$53,'Item Master'!$B$4:$B$53,"")) | C17: =IFERROR(INDEX('Log Transaction'!$E$4:$E$303,MATCH($B$7&"|"&6,'Log Transaction'!$G$4:$G$303,0)),"") | D17: =IF($A17="","",_xlfn.XLOOKUP($A17,'Item Master'!$A$4:$A$53,'Item Master'!$E$4:$E$53,0)) | E17: =IF($A17="","",$C17*$D17)
A18: =IFERROR(INDEX('Log Transaction'!$C$4:$C$303,MATCH($B$7&"|"&7,'Log Transaction'!$G$4:$G$303,0)),"") | B18: =IF($A18="","",_xlfn.XLOOKUP($A18,'Item Master'!$A$4:$A$53,'Item Master'!$B$4:$B$53,"")) | C18: =IFERROR(INDEX('Log Transaction'!$E$4:$E$303,MATCH($B$7&"|"&7,'Log Transaction'!$G$4:$G$303,0)),"") | D18: =IF($A18="","",_xlfn.XLOOKUP($A18,'Item Master'!$A$4:$A$53,'Item Master'!$E$4:$E$53,0)) | E18: =IF($A18="","",$C18*$D18)
A19: =IFERROR(INDEX('Log Transaction'!$C$4:$C$303,MATCH($B$7&"|"&8,'Log Transaction'!$G$4:$G$303,0)),"") | B19: =IF($A19="","",_xlfn.XLOOKUP($A19,'Item Master'!$A$4:$A$53,'Item Master'!$B$4:$B$53,"")) | C19: =IFERROR(INDEX('Log Transaction'!$E$4:$E$303,MATCH($B$7&"|"&8,'Log Transaction'!$G$4:$G$303,0)),"") | D19: =IF($A19="","",_xlfn.XLOOKUP($A19,'Item Master'!$A$4:$A$53,'Item Master'!$E$4:$E$53,0)) | E19: =IF($A19="","",$C19*$D19)
A20: =IFERROR(INDEX('Log Transaction'!$C$4:$C$303,MATCH($B$7&"|"&9,'Log Transaction'!$G$4:$G$303,0)),"") | B20: =IF($A20="","",_xlfn.XLOOKUP($A20,'Item Master'!$A$4:$A$53,'Item Master'!$B$4:$B$53,"")) | C20: =IFERROR(INDEX('Log Transaction'!$E$4:$E$303,MATCH($B$7&"|"&9,'Log Transaction'!$G$4:$G$303,0)),"") | D20: =IF($A20="","",_xlfn.XLOOKUP($A20,'Item Master'!$A$4:$A$53,'Item Master'!$E$4:$E$53,0)) | E20: =IF($A20="","",$C20*$D20)
A21: =IFERROR(INDEX('Log Transaction'!$C$4:$C$303,MATCH($B$7&"|"&10,'Log Transaction'!$G$4:$G$303,0)),"") | B21: =IF($A21="","",_xlfn.XLOOKUP($A21,'Item Master'!$A$4:$A$53,'Item Master'!$B$4:$B$53,"")) | C21: =IFERROR(INDEX('Log Transaction'!$E$4:$E$303,MATCH($B$7&"|"&10,'Log Transaction'!$G$4:$G$303,0)),"") | D21: =IF($A21="","",_xlfn.XLOOKUP($A21,'Item Master'!$A$4:$A$53,'Item Master'!$E$4:$E$53,0)) | E21: =IF($A21="","",$C21*$D21)
A22: =IFERROR(INDEX('Log Transaction'!$C$4:$C$303,MATCH($B$7&"|"&11,'Log Transaction'!$G$4:$G$303,0)),"") | B22: =IF($A22="","",_xlfn.XLOOKUP($A22,'Item Master'!$A$4:$A$53,'Item Master'!$B$4:$B$53,"")) | C22: =IFERROR(INDEX('Log Transaction'!$E$4:$E$303,MATCH($B$7&"|"&11,'Log Transaction'!$G$4:$G$303,0)),"") | D22: =IF($A22="","",_xlfn.XLOOKUP($A22,'Item Master'!$A$4:$A$53,'Item Master'!$E$4:$E$53,0)) | E22: =IF($A22="","",$C22*$D22)
A23: =IFERROR(INDEX('Log Transaction'!$C$4:$C$303,MATCH($B$7&"|"&12,'Log Transaction'!$G$4:$G$303,0)),"") | B23: =IF($A23="","",_xlfn.XLOOKUP($A23,'Item Master'!$A$4:$A$53,'Item Master'!$B$4:$B$53,"")) | C23: =IFERROR(INDEX('Log Transaction'!$E$4:$E$303,MATCH($B$7&"|"&12,'Log Transaction'!$G$4:$G$303,0)),"") | D23: =IF($A23="","",_xlfn.XLOOKUP($A23,'Item Master'!$A$4:$A$53,'Item Master'!$E$4:$E$53,0)) | E23: =IF($A23="","",$C23*$D23)
A24: =IFERROR(INDEX('Log Transaction'!$C$4:$C$303,MATCH($B$7&"|"&13,'Log Transaction'!$G$4:$G$303,0)),"") | B24: =IF($A24="","",_xlfn.XLOOKUP($A24,'Item Master'!$A$4:$A$53,'Item Master'!$B$4:$B$53,"")) | C24: =IFERROR(INDEX('Log Transaction'!$E$4:$E$303,MATCH($B$7&"|"&13,'Log Transaction'!$G$4:$G$303,0)),"") | D24: =IF($A24="","",_xlfn.XLOOKUP($A24,'Item Master'!$A$4:$A$53,'Item Master'!$E$4:$E$53,0)) | E24: =IF($A24="","",$C24*$D24)
A25: =IFERROR(INDEX('Log Transaction'!$C$4:$C$303,MATCH($B$7&"|"&14,'Log Transaction'!$G$4:$G$303,0)),"") | B25: =IF($A25="","",_xlfn.XLOOKUP($A25,'Item Master'!$A$4:$A$53,'Item Master'!$B$4:$B$53,"")) | C25: =IFERROR(INDEX('Log Transaction'!$E$4:$E$303,MATCH($B$7&"|"&14,'Log Transaction'!$G$4:$G$303,0)),"") | D25: =IF($A25="","",_xlfn.XLOOKUP($A25,'Item Master'!$A$4:$A$53,'Item Master'!$E$4:$E$53,0)) | E25: =IF($A25="","",$C25*$D25)
A26: =IFERROR(INDEX('Log Transaction'!$C$4:$C$303,MATCH($B$7&"|"&15,'Log Transaction'!$G$4:$G$303,0)),"") | B26: =IF($A26="","",_xlfn.XLOOKUP($A26,'Item Master'!$A$4:$A$53,'Item Master'!$B$4:$B$53,"")) | C26: =IFERROR(INDEX('Log Transaction'!$E$4:$E$303,MATCH($B$7&"|"&15,'Log Transaction'!$G$4:$G$303,0)),"") | D26: =IF($A26="","",_xlfn.XLOOKUP($A26,'Item Master'!$A$4:$A$53,'Item Master'!$E$4:$E$53,0)) | E26: =IF($A26="","",$C26*$D26)
C28: Subtotal | E28: =SUM($E$12:$E$26)
C29: Tax rate | E29: =Settings!$C$12
C30: Tax amount | E30: =$E$28*$E$29
C31: Discount | E31: 0
C32: GRAND TOTAL | E32: =$E$28+$E$30-$E$31
A34: ="Payment terms: "&Settings!$C$16
A35: =Settings!$C$17
A36: ="Thank you for supporting "&Settings!$C$8&" 💛"

Sheet Settings
A1: =HYPERLINK("#'Dashboard'!A1","🏠 Dashboard") | C1: =HYPERLINK("#'Item Master'!A1","📦 Products") | D1: =HYPERLINK("#'Log Transaction'!A1","✍️ Log Sale") | E1: =HYPERLINK("#'Invoice Generator'!A1","🧾 Invoice") | F1: =HYPERLINK("#'Start Here'!A1","🚀 Start Here")
B4: CONFIGURATION
B5: ⚙️ Settings
B6: Fill these once. Every invoice and message reads from here.
B8: 🏪 Business name | C8: Momentum Mind Store
B9: ✉️ Business email | C9: hello@momentummindstore.com
B10: 📞 Business phone | C10: +1 555 010 2030
B11: 🌐 Website / Etsy | C11: etsy.com/shop/MomentumMindStore
B12: 🧾 Tax rate | C12: 0.1
B13: 💱 Currency symbol | C13: $
B14: #️⃣ Invoice prefix | C14: MMS-
B15: 📆 Payment due (days) | C15: 14
B16: 💳 Payment terms | C16: Payment due within 14 days of invoice date.
B17: 🏦 Payment details | C17: Bank: Example Bank · Acct: 0000 0000 · Ref: your invoice no.
B19: 🔒 Rows 8–17 are the only cells you edit here. Everything else is automatic.
